Workbook

Sheet All Research
A1: COURTESY OF THE GLOBAL MOTHER DIVINE ORGANIZATION® | H1: Research Publications on
A2: Please email inquiries to: tmresearchspreadsheet@tm-women.org | H2: Transcendental Meditation® and TM-Sidhi Programs®
H3: Bibliography 1970–2026∗
H4: This spreadsheet (database) prepared by Jean Tobin, of the Global Mother Divine Organization, compiles summaries, abstracts, and data on study design and results for 485 papers published in peer-reviewed journals or other independent edited scientific publications. Most of these papers report original studies or reviews of research; a small number provide important comment or clarification regarding specific studies, including responses to critiques. A few studies examine a comprehensive multimodal approach to health that includes Transcendental Meditation®. Transcendental Meditation®, TM®, and TM-Sidhi® are protected trademarks and are used in the U.S. under license or with permission *Bibliography of research publications on Transcendental Meditation® compiled by Dr Roger Chalmers MRCP(UK) MRCGP DRCOG
H6: Column A: General Topic: Health, Mental Potential Social Behavior, World Peace
H7: Column B: Field and Collected Papers Reference (if applicable): Physiological, Psychological, Sociological
H8: Column C: Specialty Area: Academic Performance, Affective, Biochemical, Cardiovascular, Cognitive, Development of Personality, EEG, Electrophysiological, Education, Electrophysiological, Health, Intelligence, Learning, Metabolic, Motor and Perceptual, Physiological Efficiency and Stability, Productivity and Quality of Life, Rehabilitation, Review of Research
H9: Column D: Specific Results
H10: Column E: Randomized controlled trial/ Meta-analysis
H11: Column F: Year Published
H12: Column G s = Summary provided
H13: Column H: Citation/Abstract/Summary
A14: GENERAL TOPIC | B14: FIELD and Collected Papers Reference | C14: SPECIALTY AREA | D14: SPECIFIC RESULTS | E14: RCT /META | F14: YEAR
A15: Social Behavior | B15: Sociological CPVol 3Pg 2093 | C15: Rehabilitation | D15: Reduced Insomnia TM in Corrections | F15: 1978 | G15: s | H15: Abrams AI, Siegel LM. The Transcendental Meditation program and rehabilitation at Folsom State Prison: a cross-validation study. Criminal Justice and Behavior 1978 5(1):3-20 The Transcendental Meditation program in a maximum security prison was studied via cross-validation design. Significant differences were found between the Transcendental Meditation and control groups across all the inventories, indicating reduction in anxiety, neuroticism, hostility, insomnia, fewer behavior infractions, decreased resentment; decreased negativism decreased irritability; improved sleep patterns (decreased time to fall asleep, decreased awakenings per night, improved quality of sleep).
A16: Social Behavior | B16: Sociological CPVol 3Pg 2104 | C16: Rehabilitation | D16: TM in Corrections | F16: 1979 | G16: s | H16: Abrams AI, Siegel LM Transcendental Meditation and rehabilitation at Folsom Prison: response to a critique. Criminal Justice and Behavior 1979 6(1):13-21 The benefits of Transcendental Meditation reported in the previous paper were found not to be the result of selection bias or a tendency of subjects to make socially desirable, untrue responses. The article responds to the challenge posed that findings by Abrams and Siegel on the TM program at Folsom State Prison resulted from Rosenthal experimental bias effects, and that the data was parsimoniously interpreted by the authors. The authors noted that Rosenthal effects are not so pervasive that in every possible instance promising treatments should be discounted. Moreover, EPI Lie Scale data indicate that, if anything, the treatment reduced the inmates' modest tendency to make socially desirable, untrue responses. No consistent relations between levels of Lie Scale and criterion variables were found in a meta-analysis of the data. In conclusion, the potential cost effectiveness of the program, which was questioned by the critic, was supported by an analysis of preliminary recidivism rates of discharged participants.
A17: Health | B17: Physiological | C17: Cardiovascular | D17: Reduced Hypertension | F17: 1981 | G17: s | H17: Agarwal BL, Kharbanda A. Effect of transcendental meditation on mild and moderate hypertension. Journal of the Association of Physicians of India 1981 29:591-596 Reductions in systolic and diastolic blood pressure were found in mild and moderately hypertensive subjects after six months of practice of the Transcendental Meditation technique. It is suggested that Transcendental Meditation may be used as the primary treatment in such cases. Reduction of high blood pressure is of great importance for the prevention of cardiovascular disease. Sixteen patients with mild to moderate essential hypertension undertook a carefully supervised program of Transcendental Meditation (TM). After six months, there were falls in mean systolic, diastolic, and mean arterial pressures of 16.75, 9.81, and 12.12 respectively which were highly significant. Ten (62.5%) of the 16 patients were considered to have responded satisfactorily as they showed a fall of mean arterial pressure by 15 mmHg or more, or a diastolic blood pressure of less than 90 mmHg. Results are comparable to treatment with drugs. Most of the reduction in pressure took place in the first two months. A feeling of well-being was reported by nearly all the subjects.
A18: Mental Potential | B18: Psychological: Review CPVol 6 Pg 4385 | C18: Review of Research | D18: Review of Effects on Indiv & Society | F18: 1994 | G18: s | H18: Alexander CN. Transcendental Meditation. In RJ Corsini (ed.), Encyclopedia of Psychology (pp.5465-5466). New York: Wiley Interscience, 1994 This paper presents an introduction to the Transcendental Meditation Program and major scientific research findings on its effects for the individual and society.
A19: Mental Potential & Health | B19: Psychological: Review CPVol5 Pg3399 | C19: Development of Personality | D19: TC | F19: 1986 | G19: s | H19: Alexander CN, Cranson RW, Boyer RW, Orme-Johnson DW. Transcendental Consciousness: a fourth state of consciousness beyond sleep, dreaming, and waking. In J Gackenbach (ed.), Sleep and Dreams: A Sourcebook (pp.282-312). New York: Garland Publishing, 1986 Physiological research is reviewed indicating that transcendental consciousness is a unique fourth major state of consciousness.
A20: Mental Potential | B20: Psychological CP Vol5 Pg3411 | C20: Development of Personality | D20: TC+ | F20: 1990 | G20: s | H20: Alexander CN, Davies JL, Dixon CA, Dillbeck MC, Oetzel RM, Drucker SM, Muehlman JM, Orme-Johnson DW. Growth of higher stages of consciousness: Maharishi’s Vedic psychology of human development. In CN Alexander, EJ Langer (eds), Higher Stages of Human Development: Perspectives on Adult Growth (pp.286-341). New York: Oxford University Press, 1990 The authors describe how theory and research in Maharishi’s Vedic Psychology fulfills the quest of psychology to understand and promote the full range of human development. Are proposed postformal stages truly qualitatively distinct from formal operations? Kramer (1983) asserts that genuine post-formal stages should satisfy three criteria of structural change: (I) greater abstraction of thought than in formal operations, (2) hierarchical integration of formal operations, and (3) broader equilibrium (see Piaget, 197la; Inhelder & Piaget, 1958). We will briefly examine proposed post-formal theories in this volume in relation to these criteria. Many of the authors who delineate postformal stages agree about several of their main features, and it has been suggested (e.g., by Richards & Commons) that the alignment among these descriptions may reflect the universality of the underlying stages being described. However, it has yet to be demonstrated that an individual meeting developmental criteria for one proposed stage necessarily expresses the characteristics integral to the corresponding stages of the other theorists. For example, does capacity to reason about systems of systems on the level of abstract thought necessarily coexist with greater affective and self integration? This issue, as do many others raised by the expansive theorizing contained in this volume, promises to stimulate new directions and levels of developmental research. One summary generalization can be safely made: Virtually all contributors agree that an understanding of adolescent development does not provide an adequate base for comprehending the breadth, depth, and richness of potential development in adulthood. Further conceptual clarification and research on the nature of development beyond formal operations should lead to significant revision of our understanding of the possibilities for fully "mature" forms of human growth. Ultimately, how we conceive of the endpoint of development will not only influence the direction of our research agendas but either restrict or encourage our own personal development as well.
A21: Mental Potential | B21: Psychological | C21: Development of Personality | D21: Adult Growth | F21: 1990 | G21: s | H21: Alexander CN, Drucker SM, Langer EJ. Major issues in the exploration of adult growth. In CN Alexander, EJ Langer (eds), Higher Stages of Human Development: Perspectives on Adult Growth (pp.3-32). New York: Oxford University Press, 1990 What are the highest possible forms of human development? One's conception of the endpoint of development is fundamental, for it contains one's assumptions about the direction, possibilities, and dynamics of human growth. Moreover, all prior developmental stages will be viewed as progressive approximations of this goal. Contributors to this volume were asked to address this basic issue of end point. Answering this question generally requires examination of three related issues: Does development toward the endpoint proceed through qualitatively distinct stages? What mechanisms underlie this development? What major areas get developed (e.g., cognition and affect), and how do they interrelate? Based on recent theory and research, the chapters in this book provide expanded perspectives on these important issues.
A22: Mental Potential | B22: Psychological | C22: Education | D22: Management | F22: 1990 | G22: s | H22: Alexander CN, Heaton DP, Chandler HM. Promoting adult psychological development: implications for management education. Human Resource Management 1990 2:133-137 This paper addresses the critical question of what management education can do to develop the personal characteristics needed to fulfill the demand for managers. We argue that 1) psychological development underlies performance of the tasks of management, and 2)psychological development can be facilitated by appropriate technologies; therefore, 3) such a technology can be employed to develop managers and beyond. longitudinal studies of ego developmental technology, the Transcendental Meditation technique experienced unprecedented unfreezing of psychological development in adulthood. Further application of this technology may facilitate the development of managers for the demands of the twenty-first century.
A23: Mental Potential | B23: Psychological CP Vol6 Pg4325 | C23: Development of Personality | D23: TC+ | F23: 1994 | G23: s | H23: Alexander CN, Heaton DP, Chandler HM. Advanced human development in the Vedic Psychology of Maharishi Mahesh Yogi: theory and research. In ME Miller, SR Cook-Greuter (eds), Transcendence and Mature Thought in Adulthood: The Further Reaches of Adult Development (pp.39-70). Lanham, Maryland: Rowman & Littlefield, 1994 The authors describe the development of higher states of consciousness as brought to light by Maharishi Mahesh Yogi in his Vedic Psychology, and contrast this to contemporary themes of cognitive or self-development. The authors then review research demonstrating uniquely high scores on self-development among advanced practitioners in Maharishi’s Transcendental Meditation and TM-Sidhi Program.
A24: Mental Potential | B24: Psychological | C24: Education | D24: Word of Wisdom | F24: 2005 | G24: s | H24: Alexander CN, Kurth SC, Travis F, Alexander VK. Effect of practice of the children’s Transcendental Meditation technique on cognitive stage development: acquisition and consolidation of conservation. Journal of Social Behavior and Personality 2005 17(1):21-46 The results of this study on cognitive stage development in children practicing the Maharishi Word of Wisdom technique are striking. These findings suggest that practice of the Word of Wisdom technique may accelerate the rate of acquisition and especially consolidation of conservation in childhood. The transition period in the mastery of consolidation of conservation - horizontal decalage - was substantially reduced in these children. The results of this study clearly indicate that children’s practice of the Word of Wisdom technique is positively related to performance on a series of cognitive development tasks measuring conservation. All three experimental hypotheses were supported. First, the children practicing the Word of Wisdom technique, appeared to begin acquisition of conservations skills at an earlier age than controls. Second, a significantly greater proportion of the Word of Wisdom group exhibited full consolidation of conservation, as indicated by complete mastery of the conservation series. Finally, significantly fewer of the Word of Wisdom children displayed horizontal decalage as indicated by a transitional score on the conservation series. The performance of the children practicing the Word of Wisdom technique suggests phase transitions between stages rather than prolonged temporal displacement. A striking implication of this accelerated consolidation finding is that optimization of the natural growth process in childhood through the practice of the World of Wisdom technique may result in a substantial foreshortening, and in some cases, possible elimination of the developmental “irregularity” of horizontal decalage. Given that virtually all of the children who were practicing the Word of Wisdom technique were fully conserving by age 5.08 years and that complete conservation does not typically occur until 11 or 12 years of age, the strongest possible interpretation of these data would suggest that practice of the Word of Wisdom technique may accelerate consolidation of conservation by as much as 5 to 7 years in comparison to the larger population. This cross sectional study examined cognitive stage development in 47 children practicing the Word of Wisdom technique and in 47 matched controls.
A25: Mental Potential | B25: Psychological | C25: Development of Personality | D25: TC+ | F25: 1990 | G25: s | H25: Alexander CN, Langer EJ (eds). Higher Stages of Human Development: Perspectives on Adult Growth. New York: Oxford University Press, 1990 The authors describe how theory and research in Maharishi’s Vedic Psychology fulfills the quest of psychology to understand and promote the full range of human development. This research provides striking evidence that Maharishi’s Transcendental Meditation program facilitates development across four major periods of development. These findings challenge a widely held tenet in developmental psychology that quality of direct interaction with the external physical or social environment is necessarily the critical factor influencing cognitive growth. In these studies, neither external enrichment of the environment, nor training with test-related materials or even with related concepts was employed. Instead, substantial change resulted from systematically turning attention inward to intrinsically deeper levels of mind and, ultimately, pure consciousness at their source. Regardless of the subject’s initial developmental level (e.g., sometimes quite low in the prison samples: Alexander, 1982) rate of development was rapidly accelerated through experiences of pure consciousness during the TM technique. Based upon these results the authors conclude that the process of transcending through the TM program facilitates development across periods of development commonly identified by contemporary psychology, and extends this process of growth to the higher states of consciousness described by Maharishi’s Vedic Psychology. They propose that were this developmental technology widely introduced at the earliest appropriate age, development would not freeze prematurely and growth to full enlightenment would appear as the inevitable consequence of normal human development.
A26: Health | B26: Physiological CPVol 6 Pg3840 | C26: Health: Longevity | D26: Aging; Reduced Blood Pressure, Improved Cognitive Functioning and Increased Longevity | E26: RCT | F26: 1989 | G26: s | H26: Alexander CN, Langer EJ, Newman RI, Chandler HM, Davies JL. Transcendental Meditation, mindfulness, and longevity: an experimental study with the elderly. Journal of Personality and Social Psychology 1989 57(6):950-964 A meticulously controlled randomized study at Harvard University found that elderly individuals who learned the Transcendental Meditation technique showed significantly greater improvements in a variety of age-related aspects of physical and mental health and well-being than subjects taught other techniques or a no treatment control group. In particular, those who learned a relaxation procedure that attempted to imitate Transcendental Meditation technique showed no improvement on any measure. A clear majority of subjects practicing the TM technique rated their technique as particularly useful and easy to practice in contrast to lower rates for the other techniques. Most strikingly, after three years, all those who had learned the TM technique were still living in contrast to significantly lower survival rates for the other three groups and for the remaining inhabitants of the other institutions where the study was conducted. Benefits for the Elderly Demonstrating Reversal of Aging: Increased Longevity (Higher Survival Rate); Reduction of Systolic Blood Pressure to More Ideal Levels; Improved Mental Health (Improvements on Nursesi Mental Health Ratings); Increased Cognitive Flexibility (Verbal Task); Increased Learning Ability (Paired Associate Learning Task); Improvements in Self-Reported Measures of Behavioral Flexibility and Aging (Greater Ability to Cope with Inconvenience, Reduced Feelings of Being Old); Greater Sense of Well-Being (Feeling Better and More Relaxed After Transcendental Meditation; Feeling Better During Transcendental Meditation; High Interest in Transcendental Meditation; and High Ratings of the Value of Transcendental Meditation.)
A27: Social Behavior | B27: Sociological CP Vol 7 Pg4900 | C27: Rehabilitation | D27: TM in Corrections Reduced Schizophrenic Symptoms, Reduced Aggression, Decreased Anxiety | F27: 2003 | G27: s | H27: Alexander CN, Orme-Johnson DW. Walpole study of the Transcendental Meditation program in maximum security prisoners II: longitudinal study of development and psychopathology. Journal of Offender Rehabilitation 2003 36(1-4):127-160 Prison inmates in Massachusetts, USA, who learned the Transcendental Meditation program and practiced regularly over a 15-month period, in contrast to control inmates, showed significantly increased ego development, decreased aggression, reduced schizophrenic symptoms, and increased frequency of experiences of higher consciousness in comparison to members of several control groups. 271 maximum-security prisoners who were participating in either the Transcendental Meditation (TM) program, counseling, drug rehabilitation, or faith based groups. Only regular participants in the TM program changed significantly. TM subjects showed significant reductions in aggression (p < .05), especially those who meditated at least twice a week (p < .005). In addition, they showed reduced schizophrenic symptoms (p < .05), decreased trait-anxiety (p < .10, trend), and increased frequency of postconceptual experience of higher states of consciousness (p < .01)
A28: Social Behavior | B28: Sociological CP Vol 7 Pg4923 | C28: Rehabilitation | D28: TM in Corrections Reduced Recidivism | F28: 2003 | G28: s | H28: Alexander CN, Rainforth MV, Frank PR, Grant JD, Von Stade C. Walpole study of the Transcendental Meditation program in maximum security prisoners III: reduced recidivism. Journal of Offender Rehabilitation 2003 36(1-4):161-180 Prison inmates in Massachusetts, USA, who learned the Transcendental Meditation program while incarcerated showed significantly less return to prison for 30 days or longer in contrast to control groups from the same prison, as well as in a significantly lower rate of reincarceration due to new arrests. Inmates who practiced the TM Technique experienced a reduction in recidivism of 33%, which was statistically significant (p = .042). Separate comparisons showed that the TM group also had lower re-incarceration rates than each of the four other programs, with proportionate reductions in recidivism ranging from 29% to 42% (p = .007 to .073). In addition, the TM group compared to all non-meditating subjects had a lower rate of re-incarceration due to new convictions (47% lower, proportionately; p = .045) and a 27% proportionately lower rate of re-incarceration/warrant for arrest (p = .069). The pattern of reduced recidivism for TM program members was maintained in multiple regression analyses, controlling for background and release variables (e.g., parole vs. full discharge, institution of release, drug history). These findings are consistent with the proposition that the reduced psychopathology and accelerated psychological development resulting from the TM program are responsible for reductions in criminal behavior. In this study, a group who had learned the TM program (N = 53) was compared to a control group (N = 233) of inmates who did not practice the TM technique.
A29: Mental Potential | B29: Psychological CP Vol6 Pg3966 | C29: Development of Personality | D29: Self-Actualization | E29: Meta | F29: 1991 | G29: s | H29: Alexander CN, Rainforth MV, Gelderloos P. Transcendental Meditation, self-actualization, and psychological health: a conceptual overview and statistical meta-analysis. Journal of Social Behavior and Personality 1991 6(5):189-247 This meta-analysis of all research on the effects of the TM program on self-actualization, in comparison to other techniques found that the Transcendental Meditation program had 3 times the effect size of other procedures in enhancing self actualization and it’s other components (emotional maturity, integrated perspective on self and world, and resilient sense of self.) The Transcendental Meditation program was also found to lead to significant improvements on each of the twelve scales of the most common test of self-actualization. In a statistical review of 42 independent research results the TM program was found to be three times as effective as other meditation and relaxation procedures in increasing self-actualization an overall measure of positive mental health and personal development. Further analysis revealed that the technique is exceptionally effective in developing three independent components of this dimension: emotional maturity, a resilient sense of self, and a positive integrated perspective on ourselves and the world Increased Self Actualization through Transcendental Meditation in Contrast to other Procedures as Demonstrated by Meta-Analysis; Improvement in the Measured Components of Self-Actualization: Increased Time Competence (Ability to Live in the Present; Ability to Connect Past, Present, and Future Meaningfully); Increased Inner-Directedness (Independence; Self-Supportiveness); Increase Self-Actualizing Value (Holding Values of Self-Actualizing People); Increased Existentiality (Flexibility in Application of Values); Increased Spontaneity; Increased Self-Regard; Increased Self-Acceptance; Increased Nature of Man Constructive (See Man as Essentially Good); Increased Synergy (Sees Opposites of Life as Meaningfully Related); Increased Acceptance of Feelings; Increased Capacity for Intimate Contact (Warm Interpersonal Relationships); Increased Emotional Maturity; Increased Integrative Perspective on Self and World; Increased Resilient Sense of Self
A30: Health | B30: Physiological Review CPVol 6 Pg 4255 | C30: Cardiovascular Health Rehabilitation Affective, Development of Personality | D30: Comparing Techniques Reviews 4 Meta-Analyses | F30: 1994 | G30: s | H30: Alexander CN, Robinson P, Orme-Johnson DW, Schneider RH, Walton KG. The effects of Transcendental Meditation compared to other methods of relaxation in reducing risk factors, morbidity, and mortality. Homeostasis 1994 352:243-264 This paper reviews four meta-analyses that show the superiority of the Transcendental Meditation program compared to other techniques in producing deep rest, decreasing anxiety, increasing self-actualization, and decreasing substance abuse (cigarettes, drugs, alcohol). It also reviews individual well controlled studies on the beneficial effects of this technique on hypertension, mortality, medical care, and medical expenses, and discusses physiological mechanisms for these effects.
A31: Social Behavior | B31: Sociological CPVol 6Pg 4013 | C31: Rehabilitation | D31: Reduced Substance Abuse (Alcohol, Drugs and Cigarettes) | E31: Meta | F31: 1994 | G31: s | H31: Alexander CN, Robinson P, Rainforth MV. Treating and preventing alcohol, nicotine, and drug abuse through Transcendental Meditation: a review and statistical meta-analysis. Alcoholism Treatment Quarterly 1994 11(1/2):13-87 This paper presents a meta-analysis of the Transcendental Meditation program, indicating that individuals who learn this program show a significantly greater reduction in use of illegal drugs, alcohol and cigarettes than do individuals who participate in programs of relaxation, prevention or treatment. The results also showed that abstinence from illegal drugs, alcohol and cigarettes, was maintained or even increased over a long period of time among those who participated in the TM program, in contrast to high relapse rates for standard treatment programs. The meta-analysis also indicated that individuals with substance abuse problems who learned the TM program, showed significantly improved psychological health in comparison to controls. This meta-analysis of 155 studies found that the TM program was significantly more effective in reducing alcohol consumption (d=0.55) than relaxation techniques, counseling, peer pressure and DUI programs, (ds ranged from 0.07 to 0.33). In addition, a statistical meta-analysis summarizing 19 studies on the effects of the TM program found the technique produced substantial and highly significant reductions in alcohol, cigarettes and illegal drug use, with larger effects than other treatments, including standard therapies and other techniques of meditation and relaxation. Over an 18-24 month period, abstinence ranged from 51% to 89% for the TM program compared to 21% for good conventional substance abuse programs. Results of Integrative Meta-Analysis: Significantly Greater Reduction in Use of Illegal Drugs, Alcohol, and Cigarettes than Programs of Relaxation, Prevention, or Treatment; Abstinence from Illegal Drugs, Alcohol, and Cigarettes Maintained or Increased over Long Term (Relapse Prevention); Improved Psychological Health (Reduced Negative Qualities, Reduced Anxiety, Improved Positive Qualities) Among Those with Substance Abuse Problems in Comparison to Controls. Decades of efforts in the treatment of substance abuse have failed to yield a comprehensive treatment strategy that successfully addresses the multidimensional nature of chemical addiction. The current paper proposes that the Transcendental Meditation (TM) program provides a holistic, natural, and effective approach that positively impacts a constellation of factors-social, environmental, physiological, psychological, and spiritual-that influence addictive behavior. TM’s effects on smoking, drinking and use of illicit drugs tend to increase over time, suggesting a cumulative effect of regular TM practice. In contrast, it is known that success rates for standard drug treatments fall off substantially over time. For alcohol abuse, TM produced a significantly greater effect than: (1) education programs designed to foster resistance to peer-pressure; (2) prevention education programs designed to enhance self-esteem and knowledge of drug consequences (3) the average of a wide range of DUI treatment programs such as AA and therapeutic probation programs and (4) the average of other relaxation treatment programs (including biofeedback, muscle relaxation, stress-management training, and other forms of meditation). For tobacco smoking, TM produced significantly greater effects than: (1) drug prevention education programs; (2) counseling programs for smoking cessation (3) bibliotherapy; (4) pharmacological treatments for nicotine addiction (including nicotine replacement programs and clonodine therapy); and (5) “unconventional” treatment (including acupuncture, hypnosis, sensory deprivation, etc.). For illicit drugs (cannabis, hallucinogens and narcotics), TM produced significantly greater effects than: (1) preventative education programs combining peer-pressure; and (2) preventative education programs fostering self-esteem and knowledge about drugs.
A32: Mental Potential | B32: Psychological | C32: Affective | D32: Relaxation | F32: 1993 | H32: Alexander CN, Sands D. Meditation and relaxation. In FN McGill (ed.), McGill’s Survey of the Social Sciences: Psychology (pp.1499-1505). Pasadena, California: Salem Press, 1993
A33: Health | B33: Physiological | C33: Cardiovascular | D33: Reduced Hypertension and Aging/Gender | E33: RCT | F33: 1996 | G33: s | H33: Alexander CN, Schneider RH, Staggers F, Sheppard W, Clayborne BM, Rainforth MV, Salerno J, Kondwani K, Smith S, Walton K, Egan B. Trial of stress reduction for hypertension in older African Americans: II. Sex and risk subgroup analysis. Hypertension 1996 28(2):228-237 More Ideal Levels of Blood Pressure in Hypertensive Subjects who Learned the Transcendental Meditation Programme: Reduction of HIgh Systolic and Diastolic Blood Pressure Found for both Men and Women, and both High and Low Psychosocial Stress Subjects: Reduction of High Systolic and Diastolic Blood Pressure Irrespective of Score on Five other Measures of Risk for High Blood Pressure, Obesity, Alcohol Use, Physical Inactivity, Dietary Sodium-Potassium Intake and Index of all Risk Factors Combined.
A34: Health & Social Behavior | B34: Sociological CPVol6 Pg 4056 | C34: Productivity and Quality of Life Dev of Personality | D34: Decreased Insomnia Workplace Less Stress, Reduced Cigarettes and Hard Liquor | F34: 1993 | G34: s | H34: Alexander CN, Swanson GC, Rainforth MV, Carlisle TW, Todd CC, Oates RM. Effects of the Transcendental Meditation program on stress reduction, health, and employee development: a prospective study in two occupational settings. Anxiety, Stress, and Coping 1993 6:245-262 This research study found that executives and employees who learned and regularly practiced theTranscendental Meditation program, in contrast to other employees from the same worksites, showed increased employee effectiveness, increased job satisfaction, improved personal and work relationships, reduced job worry and tension, reduced trait anxiety, decreased insomnia and decreased fatigue, reduced cigarette and hard liquor use, improved health and greater calm (lower skin conductance during task performance. The groups of participants in the Transcendental Meditation program also showed, in contrast to controls, improvement on three components found to underlie each of these measures, - increased occupational coherence, increased physiological settledness, and increased satisfaction with professional and personal life. This study examined health, stress and employee development in two settings in the automotive industry; a large manufacturing plant of a Fortune 100 company and a small sales distribution company. Employees who learned the TM technique showed significantly greater improvements on a wide variety of measures, including: reduced physiological arousal; decreases in anxiety, job tension, insomnia and fatigue; reduced consumption of cigarettes and hard liquor; and improved general health.
A35: Social Behavior | B35: Sociological CP Vol 7 Pg4879 | C35: Rehabilitation | D35: TM in Corrections | F35: 2003 | G35: s | H35: Alexander CN, Walton KG, Goodman R. Walpole study of the Transcendental Meditation program in maximum security prisoners I: cross-sectional differences in development and psychopathology. Journal of Offender Rehabilitation 2003 36(1-4):97-126 Prison inmates in Massachusetts, USA, who had previously learned the Transcendental Meditation program, in contrast to control inmates, were found to display significantly higher psychological development and development of consciousness, and significnatly lower psychopathology. Significant improvements in the TM group including improved ego development (p<.0005), improved interpersonal relationships (p<.05), reduced psychopathic deviation (p<.01), reduced anxiety (p<.05), reduced aggression (p<.05), reduced tension (p<.05), and reduced introversion (p<.05)These outcomes, identify the TM program as an effective tool for promoting the psychological health and personal maturation necessary for lasting rehabilitation of maximum-security inmates.
A36: Social Behavior | B36: Sociological | C36: Rehabilitation | D36: TM in Corrections | F36: 2003 | G36: s | H36: Alexander CN, Walton KG, Orme-Johnson DW, Goodman RS, Pallone NJ (eds). Transcendental Meditation in Criminal Rehabilitation and Crime Prevention. Binghamton, New York: Haworth Press, 2003 Benefits of The TM Technique experienced in 4 prison systems as well as, wide-ranging benefits of the TM program experienced by probationers that had committed offenses ranging from drunk driving to manslaughter. A comprehensive summary describing risk factors associated with the likelihood of criminal behavior and substance misuse and summarizing research indicating how the TM program successfully addresses many of these factors. A macroscopic view of the role of the TM program in criminal rehabilitation.
A37: Health | B37: Physiological | C37: Efficiency & Stability | D37: Respiratory Changes | F37: 1970 | G37: s | H37: Allison J. Respiratory changes during Transcendental Meditation. Lancet 1970 7651:833 Breath rate decreased during the practice of the TM technique, indicating a more relaxed and rested state.
A38: Health | B38: Physiological | C38: Cardiovascular | D38: Reduced Hypertension | E38: Meta | F38: 2008 | G38: s | H38: Anderson JW, Liu C, Kryscio RJ. Blood pressure response to Transcendental Meditation: a meta-analysis. American Journal of Hypertension 2008 21(3):310-316 According to a definitive new meta-analysis of previous studies on stress reduction programs and high blood pressure, the Transcendental Meditation technique was found to produce a statistically significant reduction in high blood pressure—an effect not found with other forms of relaxation, meditation, biofeedback or stress management. Blood pressure dropped significantly in all groups practicing TM compared to the controls. The reduction in blood pressure was an average of 5 points on the systolic and 3 points on the diastolic readings. These results are not only statistically significant, they are clinically significant. These results could be expected to result in 15 - 20% less cardiovascular disease. Jim Anderson and colleagues from the University of Kentucky pooled data from nine published well controlled studies that involved a total of 711 people. Subjects ranged in age from adolescents (15-18 years) to seniors (M age 81.3 + or - 9.8 years) and included normotensive, prehypertensive and hypertensive individuals.
A39: Social Behavior | B39: Sociological | C39: Rehabilitation | D39: TM in Corrections | F39: 2003 | G39: s | H39: Anklesaria FK, King MS. The Enlightened Sentencing Project: a judicial innovation. Journal of Offender Rehabilitation 2003 36(1-4):35-46 Probationers “sentenced” to The TM Technique report less anger, decreased substance abuse,. Judges report the probationers practicing TM have greater self-esteem and self-control, positive social attitude, increased ability to secure employment. Starting in 1996, Judge David C. Mason, a Missouri circuit court judge began sentencing probationers (offenses from drunk driving to manslaughter) to learn The TM Technique and to attend classes on the technique. As of the publication of this study in 2003, 6 judges in Missouri have sentenced 100 probationers to The TM Program. Probation Officers in Missouri are also experiencing the wide range of benefits of the TM Program. Through the creative use of existing laws, the Enlightened Sentencing Project is an example of successful judicial innovation to meet a social need.
A40: Social Behavior | B40: Sociological | C40: Rehabilitation | D40: TM in Corrections | F40: 2003 | G40: s | H40: Anklesaria FK, King MS. The Transcendental Meditation program in the Senegalese penitentiary system. Journal of Offender Rehabilitation 2003 36(1-4):303-318 Between 1987 and 1989, more than 11,000 inmates and 900 correctional officers and prison administrators in 31 of the 34 prisons in the West African nation of Senegal were instructed in the Transcendental Meditation1 program. Rule infractions decreased, medical expenses went down 70%, and recidivism dropped from 90% in the pre-meditation period to less than 3% after the program was established.
A41: Health | B41: Physiological | C41: Motor & Perceptual | D41: Reaction Time | F41: 1974 | G41: s | H41: Appelle S, Oswald LE. Simple reaction time as a function of alertness and prior mental activity. Perceptual and Motor Skills 1974 38(3):1263-1268 Subjects practicing the Transcendental Meditation technique were found to have faster reactions before and after a session of the technique, compared with other subjects before and after either rest or a simple task.
A42: Health | B42: Psychologial | C42: Affective | D42: Stress Reduction | F42: 2023 | G42: s | H42: Aquino-Russell C, Aldiabat KM, Alsrayheen E. Experiences of advanced standing program nursing students and instructors practicing Transcendental Meditation. American Journal of Qualitative Research 2023 7(3):32-48. doi.org/10.29333/ajqr/13239 Little is known about the experiences of Advanced Standing Program (ASP) nursing students and instructors who practice Transcendental Meditation® (TM®). The purpose of this qualitative study was to uncover themes from the written descriptions of ASP nursing students and instructors who were taught to practice TM in order to gain a deeper understanding of how this practice might have meaning for and influence their lives and well-being. At the same time, discovering ways that TM could be incorporated into nursing education and practice as an effective stress reduction intervention and opportunity to enhance nursing care. Thematic analysis was employed. Twenty students and three instructors volunteered and were provided with education sessions by certified TM teachers involving the correct way to practice TM twice per day. Written descriptions were collected via written monthly reflective journals over 11 months. Descriptions were analyzed from the journal entries, uncovering major themes describing the experiences of participants when practicing TM and the resulting positive impact on their lives for managing stress, enhancing productivity, and improving relationships. In conclusion, recommendations involve the use of TM to be introduced and implemented as a useful stress reduction intervention tool in nursing programs for students and their instructors.
A43: Health | B43: Psychological | C43: Affective | D43: Well Being | E43: RCT | F43: 2024 | G43: s | H43: Aquino-Russell C, Bonamer JI, Hartranft S, Kutash M, Johnson A. Transcendental Meditation enriches nurses’authentic presence through caring for self and others. ﻿Journal of Holistic Nursing 2024 42(4).doi.org/10.1177/08980101241262922 The overall multimethod study involved qualitative thematic analysis (TA) and a randomized controlled trial to describe/evaluate the well-being of clinical nurses following the instruction and practice of TM during the pandemic. As part of the study, participants were provided TM instruction. Surveys were conducted at baseline, 1-month and 3-months; however, the qualitative component was only included in the 3-month survey. Following submission of the baseline survey, participants were randomized to either immediate instruction (intervention group) or delayed instruction which happened after the final 3-month survey (control group). The qualitative component of our study involved thematic analysis to describe the experiences of clinical nurses following the instruction and practice of TM during the COVID-19 pandemic.
A44: Health | B44: Physiological | C44: EEG | D44: TC | F44: 2004 | G44: s | H44: Arenander A, Travis FT. Brain patterns of Self-awareness. In B Beitman, J Nair (eds), Self-Awareness Deficits. New York: WW Norton, 2004 This chapter has introduced the concept of a foundational state of self- awareness, which is posited to be both independent and the source of conscious experiences. Research suggests that high levels of broadband frontal EEG coherence are associated with this ground state of self-awareness. This basic awareness may act as an empty canvas upon which we organize, direct, and experience the ever-changing circumstances of our lives, . Intact, highly synchronous prefrontal circuits appear to be critical to the direct experience of this ground state of awareness, as well as the transition from an episodic, meditation-dependent experience of this condition to its gradual development as a coexisting continuum across waking, dreaming, and sleeping states of consciousness. Our review supports the existence of at least two primary modes of self-awareness, one with and one without content, as well as the possibility of a third, integrated mode, in which knower and known, self and objects coexist. Future research should continue to characterize this putative ground of self-awareness and the consequences of its repeated and systematic experience on brain plasticity and function. Once such a research-based foundation is established, then the various, diverse expressions of self-awareness can be better understood as progressive layers of processing and interaction between the knower (self-awareness) and the known (the inner and outer environment). In turn, we should be in a better position to understand and effectively treat the variety of dysfunctional modes of self-awareness.
A45: Social Behavior | B45: Review Paper CPVol4 Pg 2894 | C45: Rehabilitation | D45: Reduced Substance Abuse | F45: 1980 | G45: s | H45: Aron A, Aron EN. The Transcendental Meditation program's effect on addictive behavior. Addictive Behaviors 1980 5(1):3-12 This paper reviews research showing that the Transcendental Meditation program is effective in counteracting a wide variety of addictive behaviors. The authors locate the basis of this effect in the comprehensive physiological, psychological, and social benefits which have been found to result from Transcendental Meditation.—EDITORS The last section considers practical issues in implementing TM programs in addiction treatment and preventive settings.
A46: Social Behavior | B46: Sociological CPVol 3Pg 2158 | C46: Rehabilitation | D46: Reduced Substance Abuse | F46: 1983 | G46: s | H46: Aron A, Aron EN. The pattern of reduction of drug and alcohol use among Transcendental Meditation participants. Bulletin of the Society of Psychologists in Addictive Behaviors 1983 2(1):28-33 Reduced use of tobacco, alcohol, and marijuana was found to result from the practice of the Transcendental Meditation technique. The pattern seen was one of a progressive, internally-motivated decline of drug usage as a natural consequence of positive developments in the individual's life.—EDITORS Recent studies suggest that substance abuse gradually declines and usage usually ceases after about 2 years of Transcendental Meditation (TM) practice, although the technique is seldom learned for this purpose. Many reported finding the substances less enjoyable or a growing sensitivity to their adverse physiological effects.
A47: Mental Potential | B47: Psychological CPVol3 Pg1977 | C47: Intelligence, Learning and Academic Performance, Cognitive and Affective | D47: Improved Academic Performance, Greater Moral & Social Maturity | F47: 1981 | G47: s | H47: Aron A, Orme-Johnson D, Brubaker P. The Transcendental Meditation program in the college curriculum: a four-year longitudinal study of effects on cognitive and affective functioning. College Student Journal 1981 15(2):140-146 This study found improvements in academic performance, greater moral maturity, increased orientation toward positive values, increased intelligence, increased self-confidence, increased sociability, increased psychological health and growth of social maturity in college students who practice the TM technique.
A48: Social Behavior | B48: Psychological CPVol4 Pg2474 | C48: Affective | D48: Marital Satisfaction & Adjustment | F48: 1982 | G48: s | H48: Aron EN, Aron A. Transcendental Meditation and marital adjustment. Psychological Reports 1982 51(7):887-890 This study found increase marital satisfaction and adjustment in couples who practice the TM technique. Married women who had learned the Transcendental Meditation technique showed greater marital satisfaction than matched non-meditating controls. This result was significantly greater in women who were regular in their practice of the Transcendental Meditation technique.
A49: World Peace | B49: Sociological CPVol 6Pg 4101 | C49: Quality of Life | D49: Maharishi Effect: Nation | F49: 1995 | G49: s | H49: Assimakis PD, Dillbeck MC. Time series analysis of improved quality of life in Canada: social change, collective consciousness, and the TM-Sidhi program. Psychological Reports 1995 76(3):1171-1193 Improved Quality of National Life: Improvements on a Weekly Index Including Motor Vehicle Fatalities, Homicide, and Suicide (Canada, 1983-1985); Improvements on a Monthly Index Including Motor Vehicle Fatalities, Homicide, Suicide, Cigarette Consumption, and Worker-Days Lost in Strikes (Canada, 1972-1986). Reduced violent deaths were found in Canada when the size of the Maharishi University of Management group exceeded the square root of one percent of the combined populations of the U.S. and Canada. The two studies reported in this paper found improved quality of national life in Canada during periods when the size of the group of participants in the Transcendental Meditation Sidhi program in the USA exceeded the square root of one percent of the combined national populations of the USA and Canada. The first study found significant improvement in a weekly index measured by the sum of motor vehicle fatalities, homicides, and suicides, the second study documented significant improvement in a monthly index that combined the variables of motor vehicle fatalities, homicide, suicide, cigarette consumption and work days lost in strikes.
A50: Health | B50: Physiological | C50: Affective | D50: Stress Reduction | F50: 2020 | G50: s | H50: Avvenuti G, Leoa A, Cecchettia L, Franco MF, Travis F, Caramellad D, Bernardia G, Ricciardia E, Pietrini P. Reductions in perceived stress following Transcendental Meditation practice are associated with increased brain regional connectivity at rest. Brain and Cognition 2020 139:105517. doi.org/10.1016/j.bandc.2020.105517 Transcendental Meditation (TM) is defined as a mental process of transcending using a silent mantra. Previous work showed that relatively brief period of TM practice leads to decreases in stress and anxiety. However, whether these changes are subserved by specific morpho-functional brain modifications (as observed in other meditation techniques) is still unclear. Using a longitudinal design, we combined psychometric questionnaires, structural and resting-state functional magnetic resonance imaging (RS-fMRI) to investigate the potential brain modifications underlying the psychological effects of TM. The final sample included 19 naïve subjects instructed to complete two daily 20-min TM sessions, and 15 volunteers in the control group. Both groups were evaluated at recruitment (T0) and after 3 months (T1). At T1, only meditators showed a decrease in perceived anxiety and stress (t(18) = 2.53, p = 0.02), which correlated negatively with T1-T0 changes in functional connectivity among posterior cingulate cortex (PCC), precuneus and left superior parietal lobule. Additionally, TM practice was associated with increased connectivity between PCC and right insula, likely reflecting changes in interoceptive awareness. No structural changes were observed in meditators or control subjects. These preliminary findings indicate that beneficial effects of TM may be mediated by functional brain changes that take place after a short practice period of 3 months.
A51: Health | B51: Psychologial | C51: Affective | D51: Reduced Insomnia, Anxiety Depression,Stress | F51: 2021 | G51: x | H51: Azizoddin DR, Kvaternik N, Beck M, Zhou G, Hasdianda MA, Jones N, Johnsky L, Im D, Chai PR, Boyer, EW. Heal the Healers: a pilot study evaluating the feasibility, acceptability, and exploratory efficacy of a Transcendental Meditation intervention for emergency clinicians during the coronavirus disease 2019 pandemic. Journal of the American College of Emergency Physicians Open 2021 2(6):e12619.doi.org/10.1002/emp2.12619 Abstract Objective: Emergency clinicians face elevated rates of burnout that result in poor outcomes for clinicians, patients, and health systems. The objective of this single-arm pilot study was to evaluate the feasibility of a Transcendental Meditation (TM) intervention for emergency clinicians during the coronavirus disease 2019 (COVID-19) pandemic and to explore the potential effectiveness in improving burnout, sleep, and psychological health. Methods: Emergency clinicians (physicians, nurses, and physician-assistants) from 2 urban hospitals were recruited to participate in TM instruction (8 individual or group in-person and remote sessions) for 3 months. Session attendance was the primary feasibility outcome (prespecified as attending 6/8 sessions), and burnout was the primary clinical outcome. Participant-reported measures of feasibility and validated measures of burnout, depression, anxiety, sleep disturbance, and stress were collected at baseline and the 1-month and 3-month follow-ups. Descriptive statistics and linear mixed effects models were used. Results: Of the 14 physicians (46%), 7 nurses (22%), and 10 physician-assistants (32%) who participated, 61% were female (n = 19/32). TM training and at-home meditation practice was feasible for clinicians as 90.6% (n = 29/32) attended 6/8 training sessions and 80.6% self-reported meditating at least once a day on average.Participants demonstrated significant reductions in burnout (P < .05; effect sizes, Cohen’s d = 0.43–0.45) and in symptoms of depression, anxiety, stress, and sleep disturbance (P values < .001; Cohen’s d = 0.70–0.87).
A52: Health | B52: Physiological CPVol 3 Pg1666 | C52: EEG | D52: TC | F52: 1984 | G52: s | H52: Badawi K, Wallace RK, Orme-Johnson D, Rouzeré A-M. Electrophysiologic characteristics of respiratory suspension periods occurring during the practice of the Transcendental Meditation program. Psychosomatic Medicine 1984 46(3):267-276 The combination of inner alertness, respiratory suspension, and high EEG coherence was found to characterize the state of transcendental consciousness experienced during the practice of the Transcendental Meditation technique.
A53: Health | B53: Physiological | C53: Cardiovascular | D53: Reduced Hypertension | E53: Meta | F53: 2015 | G53: s | H53: Bai Z, Chang J, Chen C, Li P, Yang K, Chi I. Investigating the effect of transcendental meditation on blood pressure: a systematic review and meta-analysis. Journal of Human Hypertension 2015 29 :653 – 662. doi:10.1038/jhh.2015.6 Twelve studies with 996 participants were assessed to examine the effect of TM on BP outcomes. The studies suggested that the reduction of systolic BP and diastolic BP was significantly different between TM groups and control groups, with approximate reductions of 4.26mmHg and 2.33mmHg, respectively, among participants in TM groups. This indicates that TM may reduce the risk of cardiovascular disease by significantly reducing BP. The heterogeneity across the included studies was low and was resolved through subgroup analyses because of the wide variation in intervention duration and participant demographics (BP level, gender and age). On the basis of the results of subgroup analyses, we observed two interesting phenomena. TM had a greater effect on individuals older than 65, those with initial systolic BP greater than 140mmHg, and women relative to younger participants (less than 65 years old), those with initial systolic BP 120–139mmHg and men, respectively.
A54: Health | B54: Psychological | C54: Affective | D54: PTSD University Students | F54: 2019 | G54: s | H54: Bandy C, Dillbeck M, Sezibera V, Taljaard L, de Reuck J, Wilks M, Shapiro D, Peycke R. Reduction of PTSD in South African university students using Transcendental Meditation practice. Psychological Reports 2019 (February) online. doi:10.1177/0033294119828036 A study was conducted on South African college students using the Transcendental Meditation technique to reduce posttraumatic stress disorder. Students meeting the criteria for possible posttraumatic stress disorder were included. Thirty-four students at the experimental university in South Africa clinically diagnosed with posttraumatic stress disorder were instructed in and practiced the Transcendental Meditation technique twice daily compared to 34 diagnosed posttraumatic stress disorder comparison students at the comparison university. The multivariate effect was significant for both the posttraumatic stress disorder symptomatology and depression. Results were significantly associated with regularity of practice. The study replicates recent findings and offers an alternative educational treatment for higher education.
A55: Mental Potential & Health | B55: Physiological | C55: EEG | D55: TC Unique State of Restful Alertness | F55: 1973 | G55: s | H55: Banquet JP. Spectral analysis of the EEG in meditation. Electroencephalography and Clinical Neurophysiology 1973 35(2):143-151 Subjects practicing the Transcendental Meditation technique showed distinctive EEG changes, including slow, high amplitude alpha activity extending to anterior channels; theta activity different from sleep; rhythmic amplitude-moderated beta waves present over the whole scalp; and synchronization of anterior and posterior channels
A56: Mental Potential & Health | B56: Physiological CPVol 3 Pg1921 | C56: EEG | D56: TC+ Increase in Vigilance and Selective Attention | F56: 1980 | G56: s | H56: Banquet JP, Lesèvre N. Event-related potentials in altered states of consciousness. Progress in Brain Research 1980 54:447-453 Practitioners of the Transcendental Meditation program were found to have faster reactions with fewer mistakes, and a shorter latency and larger amplitude of visual evoked potentials, indicating an increase in the capacity for selective attention and an improved level of vigilance. Note: In this paper the phrase ‘altered states of consciousness’ refers to higher states of consciousness developed through the TM program.
A57: Mental Potential & Health | B57: Physiological | C57: EEG | D57: TC Unique state of Restful Alertness | F57: 1974 | G57: s | H57: Banquet JP, Sailhan M. Analyse E.E.G. d’états de conscience induits et spontanés. Revue d’Electroencéphalographie et de Neurophysiologie Clinique 1974 4(3):445-453 Significant differences found between the TM technique and relaxation and the TM technique and stages I and II of sleep.
A58: Health | B58: Psychological | C58: Affective | D58: PTSD | F58: 2018 | G58: s | H58: Barnes VA. Transcendental Meditation and treatment for post-traumatic stress disorder (Editorial comment). The Lancet Psychiatry 2018 5(12):946-947. doi.org/10.1016/ <http://doi.org/10.1016/> S2215-0366(18)30423-1A key challenge in military medicine has been the treatment of the mental health of military service members who have been deployed in operations in recent years. The most effective course of treatment for post-traumatic stress disorder (PTSD) has been highly debated and is a central focus in the military community because of the large number of service members returning from deployment with PTSD. 1 More than a third of patients with PTSD do not recover even after many years, showing PTSD to be a chronic and costly illness to service members, their families, and society as a whole. 2 Traditional treatment of PTSD has not been uniformly successful because of comorbidities, side-effects of drug therapy, and time and energy needed for psychotherapy. 3 Pharmacotherapy has shown insufficient benefit in the treatment of PTSD, 4 while adherence and the treatment success of various psychotherapies has been disappointing. When patients with PTSD do not respond to traditional treatment, new approaches should be considered.
A59: Social Behavior | B59: Psychological Stress Redcution CPVol 7 Pg4798 | C59: Development of Personality | D59: Education Adolescent Behavior | E59: RCT | F59: 2003 | G59: s | H59: Barnes VA, Bauza LB, Treiber FA. Impact of stress reduction on negative school behavior in adolescents. Health and Quality of Life Outcomes 2003 1(1):10 This random assigned study found that adolescent students who learned the Transcendental Meditation technique, and participated in daily group practice, showed decreased absenteeism, reduced school rule infractions, and fewer suspension days due to behaviour problems, in contrast to control students who participated in a health education course for an equivalent amount of time each day. The TM group had lower rates of absenteeism, suspensions and school rule violations than the control group.
A60: Health | B60: Physiological | C60: Cardiovascular | D60: Reduced Left Ventricular Mass | E60: RCT | F60: 2012 | G60: s | H60: Barnes VA, Kapuku GK, Treiber FA. Impact of Transcendental Meditation on left ventricular mass in African American adolescents. Evidence-Based Complementary and Alternative Medicine 2012 923153. doi:10.1155/2012/923153 Increased left ventricular mass (LVM) has long been known to increase the risk for coronary artery disease (CAD), congestive heart failure, stroke, cardiac arrhythmias, and sudden death. An early sign of ventricular remodeling is increased left ventricular mass (LVM) which over time may lead to left ventricular hypertrophy, the strongest predictor of cardiovascular morbidity and mortality, other than advancing ageThe successful implementation of the intervention points to the potential of school-based stress reduction programs as a means of decreasing likelihood of early onset of LVH (left ventricular hypertrophy) in high-risk youth. These findings indicate that among a group of prehypertensive African American adolescents, 4 months of TM compared to heath education resulted in a significant decrease in LVMI, and these changes were maintained at 4-month follow-up. Methods. 62 (30 TM; 32 CTL) African American adolescents (age 16.2 ± 1.3 years) with high normal systolic BP were randomly assigned to either 4-month Transcendental Meditation (TM) or health education control groups. The echocardiographic-derived measure of LVM index (LVMI = LVM/ht2.7) was measured before and after the 4-month TM study and at 4-month followup. 2D-guided M-mode echocardiography using a Hewlett Packard 5500 echosonograph was used to determine LVMI. Results. The TM group exhibited a greater decrease in LVMI at 4-month followup compared to the CTL group (−2.6 versus +0.3gm/ht2.7, P < 0.04). The TM group exhibited a lesser increase in BMI at 4-month follow-up compared to the CTL group (0.2 ± 1.6 versus 1.1 ± 1.4, P < 0.03).
A61: Health | B61: Psychological | C61: Affective | D61: PTSD | F61: 2016 | G61: s | H61: Barnes VA, Monto A, Williams JJ, Rigg JL. Transcendental Meditation® and psychotropic medication use among active duty military service members with anxiety and PTSD. Military Medicine 2016 181(1):56-63. doi:10.7205/MILMED-D-14-00333 Transcendental Meditation reduces medication reliance in soldiers with PTSD Savannah, GA - Research from the Eisenhower Army Medical Center at Fort Gordon GA suggests that the Transcendental Meditation™ program reduces the use of medication reliance and reduces psychological symptom severity of soldiers with anxiety and post traumatic stress. Fort Gordon, GA — Charts were reviewed for 74 active duty military service members diagnosed with Post-Traumatic Stress Disorder or Anxiety Disorder Not-Otherwise-Specified, of whom 37 had participated in the Transcendental Meditation™ program. Scores were compared on measures of symptom severity as well as the amount of psychiatric medication prescribed to determine whether participation in Transcendental Meditation™ in addition to psychotherapy was more effective in relieving psychological symptoms than psychotherapy alone. Changes in medication dosages and psychological symptom severity were measured from the baseline at one, two, three and six months from the start of treatment for both groups. Results indicated that over six months, the group practicing Transcendental Meditation™ reduced their medication usage and experienced an overall decrease in the severity of their psychological symptoms, while the control group showed a small increase in symptom severity with only a small reduction in medication usage. These findings suggest benefit of Transcendental Meditation™ as a practical treatment method for use in military treatment facilities. Relief from common symptoms of combat trauma is a necessary aspect of comprehensive mental health treatment for the military community. The objective of the study was to determine whether the regular practice of Transcendental Meditation (TM) decreased the need for psychotropic medications required for anxiety and post-traumatic stress symptom management and increased psychological well-being. Records of 74 military Service Members with documented post-traumatic stress or Anxiety Disorder Not Otherwise Specified were followed in a chart review. Of those Service Members, 37 practiced TM and 37 did not. At one month, 83.7% of the TM group stabilized, decreased or ceased medications and 10.8% increased medication dosage, compared to 59.4% of controls that showed stabilizations, decreases or cessations and 40.5% that increased medications (p<.03). A similar pattern was observed after two (p<.27), three (p<.002) and six months (p<.34). There was a 20.5% difference between groups in severity of psychological symptoms after six months, that is, the control group experienced an increase in symptom severity when compared the group practicing TM. These findings suggest the benefit of TM as an adjunctive treatment modality in military treatment facilities.
A62: Health | B62: Physiological | C62: Cardiovascular | D62: Reduced Hypertension in Youth & Adults | F62: 2006 | G62: s | H62: Barnes VA, Orme-Johnson DW. Clinical and pre-clinical applications of the Transcendental Meditation program in the prevention and treatment of essential hypertension and cardiovascular disease in youth and adults. Current Hypertension Reviews 2006 2(3):207-218 This study supports previous and subsequent research showing, clinically important reductions in blood pressure and that sustained blood pressure changes of the magnitude produced by TM would be associated with substantially decreased risk of heart attack and stroke, the leading cause of mortality worldwide.
A63: Health | B63: Physiological | C63: Cardiovascular | D63: Reduced Hypertension | F63: 2008 | G63: s | H63: Barnes VA, Orme-Johnson DW. El impacto de la reduccion del estres en el hypertension esencial y las enfermedades cardiovasculares. Revista Internacional De Ciencias Del Deporte (International Journal of Sports Science) 2008 4(12):1-30 This study supports previous and subsequent research showing, clinically important reductions in blood pressure and that sustained blood pressure changes of the magnitude produced by TM would be associated with substantially decreased risk of heart attack and stroke, the leading cause of mortality worldwide.
A64: Health | B64: Physiological | C64: Cardiovascular | D64: Research Review Update | F64: 2012 | G64: s | H64: Barnes VA, Orme-Johnson DW. Prevention and treatment of cardiovascular disease in adolescents and adults through the Transcendental Meditation Program®: a research review update. Current Hypertension Reviews 2012 8(3):227-242 The pathogenesis and progression of cardiovascular diseases are thought to be exacerbated by stress. Basic research indicates that the Transcendental Meditation® technique produces acute and longitudinal reductions in sympathetic tone and stress reactivity. In adolescents at risk for hypertension, the technique has been found to reduce resting and ambulatory blood pressure, left ventricular mass, cardiovascular reactivity, and to improve school behavior. Research on adults with mild or moderate essential hypertension has reported decreased blood pressure and reduced use of anti-hypertensive medication. The technique has also been reported to decrease symptoms of angina pectoris and carotid atherosclerosis, to reduce cardiovascular risk factors, including alcohol and tobacco use, to markedly reduce medical care utilization for cardiovascular diseases, and to significantly decrease cardiovascular and all-cause morbidity and mortality. These findings have important implications for inclusion of the Transcendental Meditation program in efforts to prevent and treat cardiovascular diseases and their clinical consequences. Media Summary excerpt: In teens, the TM technique has been found to reduce blood pressure, improve heart structure and improve school behavior. According to the paper, the technique has been shown to be a safe alternative. The NIH-sponsored clinical trials conducted with TM mentioned in this review did not observe any adverse effects from TM practice. In adults the technique reduced stress hormones and other physiological measures of stress and produced more rapid recovery from stress, decreased blood pressure and use of blood pressure medication, decreased heart pain in angina patients, cleared the arteries, reducing the risk of stroke, improved distance walked in patients with congestive heart failure, and decreased alcohol and tobacco use, anxiety, depression, and medical care usage and expenditures. The technique also decreased risk of death from heart disease, cancer, and all causes.
A65: Health | B65: Psychological | C65: Affective | D65: PTSD | F65: 2013 | G65: s | H65: Barnes VA, Rigg JL, Williams JJ. Clinical case series: treatment of PTSD with Transcendental Meditation in active duty military personnel. Military Medicine 2013 178(7):e836-40. doi:10.7205/MILMED-D-12-00426 Active duty U.S. Army Service Members previously diagnosed with post-traumatic stress disorder (PTSD) were selected from review of patient records in the Traumatic Brain Injury Clinic at the Department of Defense Eisenhower Army Medical Center at Fort Gordon in Augusta, Georgia. Patients agreed to practice the Transcendental Meditation (TM) technique for 20 minutes twice a day for the duration of a 2-month follow-up period. Three cases are presented with results that show the feasibility of providing TM training to active duty soldiers with PTSD in a Department of Defense medical facility. Further investigation is suggested to determine if a TM program could be used as an adjunct for treatment of PTSD. Impact of this report is expected to expand the complementary and alternative evidence base for clinical care of PTSD.
A66: Health | B66: Physiological CP Vol7 Pg4728 | C66: Cardiovascular | D66: Reduced Hypertension Increased Longevity | E66: RCT | F66: 2005 | G66: s | H66: Barnes VA, Schneider RH, Alexander CN, Rainforth M, Staggers F, Salerno, J. Impact of Transcendental Meditation on mortality in older African Americans with hypertension—eight-year follow-up. Journal of Social Behavior and Personality 2005 17(1):201-216 This follow-up study found that elderly individuals with hypertension who were randomly assigned to learn the Transcendental Meditation technique showed significantly reduced mortality due to cardiovascular disease after eight years, in contrast to individuals assigned to a health education control group. During the eight years of follow up covered in this study, older African Americans with mild hypertension who practiced the TM technique showed lower mortality rates from cardiovascular disease compared to behavioral health education controls. In the intent-to-treat analysis, the adjusted relative risk for cardiovascular disease mortality of the TM group compared with Health Education was significantly reduced by 81%. The adjusted relative risk for all cause mortality of the TM group compared with Progressive Muscle Relaxation showed a trend with 57 % reduction in the analysis at 3 months. The adjusted relative risk for cancer of the TM group was reduced by 68% as compared with Health Education. This data suggests long term efficacy in reducing risk of mortality in older African Americans in a low socioeconomic status, inner city primary health care setting. To our knowledge this is the first controlled trial assessing the effects of stress reduction or any non-pharmacological intervention for hypertension for mortality in a high risk population.
A67: Health | B67: Physiological CP Vol 7 Pg5118 | C67: Cardiovascular | D67: Reduced Hypertension Stress Reduction | F67: 1997 | G67: s | H67: Barnes VA, Schneider RH, Alexander CN, Staggers F. Stress, stress reduction, and hypertension in African Americans. Journal of the National Medical Association 1997 89(7):464-476 This study supports previous and subsequent research showing, clinically important reductions in blood pressure and that sustained blood pressure changes of the magnitude produced by TM would be associated with substantially decreased risk of heart attack and stroke, the leading cause of mortality worldwide.
A68: Health | B68: Physiological CP Vol 7 Pg4694 | C68: Cardiovascular | D68: Reduced Hypertension Increased Longevity | E68: RCT | F68: 2001 | G68: s | H68: Barnes VA, Treiber FA, Davis H. Impact of Transcendental Meditation on cardiovascular function at rest and during acute stress in adolescents with high normal blood pressure. Journal of Psychosomatic Research 2001 51(4):597-605 This randomized controlled study that examined the impact of the TM practice on BP reactivity in African American adolescents with high normal resting systolic blood pressure found that compared to the control group subjects, TM subjects exhibited significantly greater decreases from pre to post intervention in systolic blood pressure, heart rate and cardiac output reactivity to a car driving stressor and reduced systolic blood pressure reactivity to a social stressor interview. The study also found that the TM group exhibited a statistically significant 4.8-mmHg decreases in resting systolic blood pressure from pre-intervention to two months post-intervention, compared with an increase in 2.6-mmHg in the control group. These findings suggest that the TM practice may provide protection from the detrimental effects of exaggerated cardiovascular stress reactivity.
A69: Health | B69: Physiological CP Vol 7 Pg4704 | C69: Cardiovascular | D69: Reduced Ambulatory Blood Pressure Hypertension Education Adolescent | E69: RCT | F69: 2004 | G69: s | H69: Barnes VA, Treiber FA, Johnson MH. Impact of stress reduction on ambulatory blood pressure in African American adolescents. American Journal of Hypertension 2004 17(4):366-369 One hundred African American teenagers with blood pressure at the high end of normal were randomly assigned to two groups: One group learned TM and meditated twice a day for four months, whereas the other (control group) received health education lectures for a similar amount of time. At the end of the study, the TM group showed a significant drop in blood pressure compared with the control group, an effect that still held four months after the study ended. The TM group also had lower rates of absenteeism, suspensions and school rule violations than the control group.
A70: Health | B70: Physiological CPVol 7 Pg 4572 | C70: Cardiovascular | D70: Reduced Hypertension | F70: 1999 | G70: s | H70: Barnes VA, Treiber FA, Turner JR, Davis H, Strong WB. Acute effects of Transcendental Meditation on hemodynamic functioning in middle-aged adults. Psychosomatic Medicine 1999 61(4):525-531 Researchers who used impedance cardiography to measure total vascular peripheral resistance found that both blood pressure and total peripheral resistance decreased during the TM technique, suggesting an underlying hemodynamic mechanism for its cardio-protective effects.
A71: Health | B71: Psychological | C71: Affective | D71: PTSD Reduction | E71: RCT | F71: 2021 | G71: s | H71: Bellehsen M, Stoycheva V, Cohen BH, Nidich S. A pilot randomized controlled trial of Transcendental Meditation as treatment for posttraumatic stress disorder in veterans. Journal of Traumatic Stress 2021. doi.org/10.1002/jts.22665 This RCT demonstrated the efficacy of TM as a treat- ment for veterans struggling with PTSD. The between-group effects were robust for most outcomes, including PTSD symptom severity, depression, anxiety, and sleep problems. Differences in quality of life and anger were not statistically significant between groups. Within-group effects were robust for the TM group for all variables except anger. On the CAPS-5 measure for PTSD, 50.0% of participants in the TM group demonstrated a meaningful reduction in PTSD symptoms, and 50.0% no longer met the criteria for a PTSD diagnosis after 3 months of intervention. Compared to the control condition, TM was additionally associated with score improvements on self-report measures PTSD, depression, and anxiety symptoms as well as sleep problems. Only one participant in the TM group dropped out of the study, and 85.0% completed at least eight TM treatment sessions, suggesting that this was a tolerable intervention. The present findings are consistent with past studies that document improvement among veterans with PTSD symptoms in uncontrolled and nonrandom allocation studies (Barnes et al., 2016; Rosenthal et al., 2011) as well as in a recent large RCT (Nidich et al., 2018). The current study adds to a growing body of research suggesting that TM can have a meaningful impact on the management of PTSD and associated symptoms in veteran populations. This may be due to the amelioration of hyperarousal symptoms, as TM practice has been shown to attenuate physiological responses to stressful stimuli (Orme-Johnson, 1973). In addition, TM has been found to decrease trait anxietyand negative responses in various circumstances (Nidich et al., 2016; Orme-Johnson & Barnes, 2014). The strengths of the present study included a randomizedstudy design, with allocation concealment and blinded testing.The study had low attrition rates for both arms and included veterans who had received prior treatment for PTSD. The percentages of participants in the TM group who no longer met the criteria for PTSD diagnostic status and demonstrated clinically meaningful reductions in PTSD symptoms and were large and consistent with prior research. The weaknesses of the present study included a lack of a time-and-attention control; the exclusion of participants with comorbidities, such as substance dependence; and an absence of a follow-up period to assess longer-term stability of change as well as sustainment of meditation practice. Transcendental Meditation holds significant promise as a treatment for PTSD and may also improve associated factors, such as depressive and anxiety symptoms and sleep problems. The non–trauma-focused nature of TM practice may be appealing to veterans who avoid trauma-based therapies or do not respond to treatment. Future larger, multisite trials would further the generalizability of the present findings and could extend the follow-up time. Additional studies on specific subgroups such, as female veterans, veterans with comorbid depression, or veterans with traumatic brain injury may provide additional information on the value of TM practice within these groups.
A72: Mental Potential | B72: Psychological CP Vol 7 Pg4797 | C72: Intelligence, Learning and Academic Performance | D72: Emotions Education Adolescents Middle School | E72: RCT | F72: 2003 | G72: s | H72: Benn R. Transcendental Meditation (TM) and emotional functioning in fifth grade students. Focus on Alternative and Complementary Therapies 2003 8:480-481 Fifth-grade students who learned the Transcendental Meditation technique, in contrast to control students, showed increased positive affect, reduced negative affect, increased positive mood, and increased adaptability. This study examined the effects of Transcendental Meditation (TM) on social-emotional development and academic performance in early adolescence. Meditation was hypothesized to increase positive affect, decrease negative emotions and improve academic performance in middle school students. Forty-four African-American fifth grade students enrolled in a charter middle school were randomized into two groups. One group of students was instructed in TM and subsequently practiced meditation for 10 minutes, two times a day during the school day with teachers and students in older grades. At the time of school based meditation, the control group of students remained in their classrooms with their teachers and had assigned free time. Study participants completed self-report survey scales that assessed emotional well-being, emotional intelligence, anxiety and anger at baseline, three, nine and 15 months post-instruction in meditation. Participants' grades for academic subjects and study habits/ behaviors were coded from student records at semester time points that closely paralleled study assessment intervals. Multiple regression models were fitted to each outcome measure, controlling for the main grouping variable (mediation or not) as well as all other covariates of interest (e.g. free and reduced lunch, gender). For the 15-month academic measures, a linear regression model with normal error was used, and for non-academic measures, a repeated measures regression model with normal error was employed with an exchangeable correlation structure.
A73: Mental Potential | B73: Psychological CPVol 2 Pg 840 | C73: EEG | D73: Maximizing Brain Utilization | F73: 1977 | G73: s | H73: Bennett JE, Trinder J. Hemispheric laterality and cognitive style associated with Transcendental Meditation. Psychophysiology 1977 14(3):293-296 Subjects who practice the TM technique showed a greater degree of lateral asymmetry on analytical and spatial tasks than a control group, indicating improved utilization of that part of the brain most suited to a specific task.
A74: Mental Potential | B74: Psychological | C74: Development of Personality | D74: Self-Actualization Self-Esteem, Ego Strength | F74: 1976 | G74: s | H74: Berg WP, Mulder B. Psychological research on the effects of the Transcendental Meditation technique on a number of personality variables. Gedrag: Tijdschrift voor Psychologie (Behaviour: Journal of Psychology) 1976 4:206-218 Subjects practicing the Transcendental Meditation technique were found to increase in self-esteem, ego strength, satisfaction and self-actualization. Significant reductions in physical and social inadequacy, neuroticism, depression, and rigidity were found in short term meditators (9 weeks after learning TM), whereas no change occurred in controls. In comparison with non-meditating control subjects, long term meditators (mean time of practice one and one-half years) showed remarkably higher levels of self-esteem, satisfaction, ego strength, self-actualization, and trust in others, as well as improved self image. Long term meditators also showed remarkably less neuroticism, depression, and sensitivity to criticism compared with non-meditating controls. these results indicate that the practice of the Transcendental Meditation technique allows development of a more harmonious personalty in the direction of self-actualization.
A75: Health | B75: Psychological | C75: Affective | D75: Reduction in Stress, Anxiety, Anger, Depression, Fatigue, Improved Self-Esteem | E75: RCT | F75: 2020 | G75: s | H75: Bleasdale JE, Peterson MC, Nidich S. Effect of meditation on social/emotional well-being in a high-performing high school. Professional School Counseling 2020 23(1):1-8. doi.org/10.1177/2156759X20940639 This study explored the impact of a meditation program on stress, anxiety, and depression in a high-performing high school. Using a randomized controlled design with 52 students, the study took place over 4 months. Students participated in Transcendental Meditation (treatment) or silent reading (active control) twice daily.We observed significant reductions in perceived stress (p . .040), anxiety (p . .028), anger (p . .047), depression (p . .024), and fatigue (p . .075), and improvement in self-esteem (p . .054). The program has important implications for school counselors because of the impact on social/emotional well-being
A76: Social B | B76: Sociological | C76: Rehabilitation | D76: Reduced Substance Abuse | F76: 1994 | G76: s | H76: Bleick CR. Case histories: using the Transcendental Meditation program with alcoholics and addicts. Alcoholism Treatment Quarterly 1994 11(3/4):243-269 Case Histories: Using the Transcendental Meditation Program with Alcoholics and Addicts. A Transcendental Meditation (TM) program for alcoholics and addicts has been operating since autumn of 1986 on the Los Angeles Westside, using the facilities of the CLARE (Community Living for Alcoholics by Rehabilitation and Education) Foundation, an alcohol recovery agency headquartered in Santa Monica. Our inaugural introductory lecture was organized by a CLARE volunteer for a CLARE staff meeting. Thereafter introductory lectures were publicized through posters at CLARE facilities and by word of mouth of meditators at their Alcoholics Anonymous (AA) (see Alcoholics Anonymous World Services, Inc., 1976) or other Twelve Step program meetings, including Narcotics Anonymous (NA) and Cocaine Anonymous (CA).
A77: Social Behavior | B77: Sociological CPVol5 Pg 3123 | C77: Rehabilitation | D77: TM in Corrections | F77: 1987 | G77: s | H77: Bleick CR, Abrams AI. The Transcendental Meditation program and criminal recidivism in California. Journal of Criminal Justice 1987 15(3):211-230 Practice of TM during incarceration reduces recidivism. TM parolees had lower re-conviction rates (46.7%) compared to statewide paroles at 6 months (p<.004), 1 year, (p<.004), 2 years (p<.002) and 30-40% reduced recidivism compared to controls at 1 year (p=.0007), 3 years(p=.007). and 5 years (p=.02). 59 percent of the mediators who were surveyed in prison and not yet released were still meditating. Subjects and Data Collection: From 1975 to 1982, a total of 153 male inmates at Folsom Prison volunteered to learn the TM program. By October 1982, all had been paroled. For each TM subject, a non-meditating control subject was selected from the Folsom Prison records by matching closely on parole year, race, and offense, and matching approximately on prior commitment record, age, and history of drug abuse. For both subjects in a matched pair, the date on which the experimental subject learned the TM technique was taken as the date of entry into the study. Because the California Department of Corrections (CDC) discards records for deceased parolees, subjects who were deceased at time of data collection in 1991 were excluded. Subjects also were dropped if they were: paroled out of state or to Federal custody, serving a parole violation at time of entry into the study, found not guilty of the offense for which they were incarcerated, or if either their parole out of state or to Federal custody, serving a parole violation at time of entry into the study, found not guilty of the offense for which they were incarcerated, or if either their parole date or re-arrest date was missing. These criteria led to inclusion of data on 248 subjects, 120 of whom had learned the TM technique and 128 of whom were controls.
A78: Health | B78: Physiological | C78: Cardiovascular | D78: Myocardial Blood Flow | F78: 2019 | G78: s | H78: Bokhari S, Schneider RH, Salerno JW, Rainforth M, Gaylord-King C, Nidich S. ﻿Effects of cardiac rehabilitation with and without meditation on myocardial blood flow using quantitative positron emission tomography: a pilot study. Journal of Nuclear Cardiology 2019. doi: 10.1007/s12350-019-01884-9. [Epub ahead of print] Abstract BACKGROUND: Psychosocial stress is recognized as a risk factor for coronary heart disease (CHD). High rates of CHD in African-Americans may be related to psychosocial stress. However, standard cardiac rehabilitation (CR) usually does not include a systematic stress-reduction technique. Previous studies suggest that the Transcendental Meditation (TM) technique may reduce CHD risk factors and clinical events. This pilot study explored the effects of standard CR with and without TM on a measure of CHD in African-American patients. METHODS: Fifty-six CHD patients were assigned to CR, CR + TM, TM alone, or usual care. Testing was done at baseline and after 12 weeks. The primary outcome was myocardial flow reserve (MFR) assessed by 13N-ammonia positron emission tomography (PET). Secondary outcomes were CHD risk factors. Based on guidelines for analysis of small pilot studies, data were analyzed for effect size (ES). RESULTS: For 37 patients who completed posttesting, there were MFR improvements in the CR + TM group (+20.7%; ES = 0.64) and the TM group alone (+12.8%; ES = 0.36). By comparison, the CR-alone and usual care groups showed modest changes (+ 5.8%; ES = 0.17 and - 10.3%; ES = - 0.31), respectively. For the combined TM group, MFR increased (+ 14%, ES = 0.56) compared to the combined non-TM group (- 2.0%, ES = - 0.08). CONCLUSIONS: These pilot data suggest that adding the TM technique to standard cardiac rehabilitation or using TM alone may improve the myocardial flow reserve in African-American CHD patients. These results may be applied to the design of controlled clinical trials to definitively test these effects. TRIAL REGISTRATION: ClinicalTrials.gov registration # NCT01810029.
A79: Social Behavior | B79: Psychological | C79: Affective | D79: Reduced Compassion Fatigue in Nurses | F79: 2019 | G79: s | H79: Bonamer JR, Aquino-Russell C. Self-care strategies for professional development: Transcendental Meditation reduces compassion fatigue and improves resilience for nurses. Journal for Nurses in Professional Development 2019 35(2):93-97. doi:10.1097/NND.0000000000000522 Abstract The Transcendental Meditation technique was provided to 27 nurses across levels and areas of the organization. Quantitative tools measured the effect on nurses' compassion fatigue and resilience. Paired-sample t test analyses revealed significant improvements in the phenomena studied. Further, resilience showed a large significant, inverse relationship with burnout. This study contributes new knowledge for an innovative self-care strategy to improve resilience and reduce compassion fatigue and burnout among nurses. PMID: 30741919 DOI: 10.1097/NND.0000000000000522 [Indexed for MEDLINE]
A80: Health | B80: Psychological | C80: Affective | D80: Reduced PTSD, Anxiety, Burnout, Improving Multi-dimensional Well-Being and Flourishing | F80: 2023 | G80: s | H80: Bonamer JI, Kutash M, Hartranft SR, Aquino-Russell C, Bugajski A, Johnson A. Clinical nurse well-being improved through Transcendental Meditation: a multimethod randomized controlled trial. The Journal of Nursing Administration 2023. doi: 10.1097/NNA.0000000000001372 OBJECTIVE: To evaluate the impact of Transcendental Meditation® (TM®) practice on the multidimensional well-being of nurse clinicians affected by the COVID-19 pandemic. BACKGROUND: The health of clinical nurses has substantial impact on both the availability of a nursing workforce and the quality and safety of patient care.TMimproved health and coping strategies across many populations. METHODS: Clinical nurses were recruited from 3 Magnet®-designated hospitals during the COVID-19 pandemic. Well-being outcomes included flourishing, burnout, anxiety, and posttraumatic stress disorder. Participants were randomized following completion of baseline surveys into immediate (intervention) or delayed (control) TM instruction. Surveys were repeated at 1 and 3 months following baseline survey or TM instruction. Repeated-measures analysis of variance compared differences in groups over time. RESULTS: Across the 3 sites, there were 104 clinical nurse participants. Repeated-measures analysis of variance showed significant medium to large effects in improvement over time in well-being measures for the intervention group. CONCLUSIONS: TM improved multidimensional well-being of clinical nurses by reducing posttraumatic stress disorder, anxiety, and burnout and improving flourishing. TMis easy to practice anywhere. The benefits are immediate and cumulative. Organizations and individual nurses can use TM to support clinical nurses in the difficult and meaningful work of patient care, especially in challenging times. Future studies may consider the feasibility of integrating TM into clinical shifts and evaluating its impact on patient and organizational outcomes.
A81: Health | B81: Review Paper CP Vol 4 Pg2790 | C81: Health | D81: TC+ | F81: 1980 | G81: s | H81: Blicher B, Blondeau F, Choquette C, Deans A, Drouin P, Glaser J, Thibaudeau P. Méditation Transcendantale: revue de la littérature scientifique. Le Médecin du Québec 1980 15(8):46-66 The Transcendental Meditation and TM-Sidhi program is found to result in a coherent state of neurological functioning which is maintained during activity. This forms the basis for optimal human performance and the development of higher states of consciousness as described in the Vedic Literature.
A82: Health | B82: Physiological | C82: Cardiovascular | D82: Reduced Hypertension | F82: 2006 | G82: s | H82: Bovee JC. Effects of Transcendental Meditation on blood pressure: a literature review. Modern Psychological Studies 2006 11:1-11 Many prevention and treatments methods exist for hypertension, but not all are effective or easy to incorporate into one’s life. Stress-reduction methods, including Transcendental Meditation (TM), has been suggested as such a method, but have received inconsistent reviews about its effect on blood pressure. This literature review of twelve clinical studies concludes patients who practice TM can significantly reduce blood pressure. The technique was found to be effective for groups at high risk for hypertension, such as African-Americans, as well as low-risk groups. TM also appears to be more effective than progressive muscle relaxation, another popular stress-management technique. TM should be incorporated into plans for treatment of hypertension. In all but three (Blackwell et al., 1976; Pollack et al., 1977; Castillo-Richmond et al., 2001) of the 11 studies reviewed, participants who practiced TM reduced their blood pressure. Two of the studies that did not support the hypothesis, lacked control groups and were methodologically weak (Blackwell et al., 1976; Pollack et al., 1977). Of the eight controlled studies, seven support the hypothesis that TM significantly lowers blood pressure. In the only study that failed to show these results, change in blood pressure was a secondary outcome and not investigated in full (Castillo-Richmond et al., 2001). A more in depth analysis and statistical control of confounding variables may have produced different results. The findings of the controlled trials are convincing and generalizable. The majority of the studies carefully matched treatments for daily time commitment, attention from instructors, and checked for differences in expected treatment benefits between groups. These precautions help to rule out the contributions of non-specific factors simply associated with being part of an intervention. Many studies controlled for anthropometric and lifestyle differences between groups that existed at baseline. Results are generalizable to both resting blood pressure (Alexander et al., 1996; Barnes et al., 2001; Schneider et al., 1995; Schneider et al., 2005; Seer & Raeburn, 1980; Wenneberg et al., 1997) and ambulatory blood pressure (Barnes et al., 2004; Wenneberg et al., 1997), to normotensives (Barnes et al., 2001; Barnes et al., 2004, Wenneberg et al., 1997) and hypertensives (Alexander et al., 1996; Schneider et al., 1995; Schneider et al., 2005; Seer & Raeburn, 1980), across ethnicities and ages. TM was found to be a successful antihypertensive method across different lifestyle risk factors (Alexander et al., 1996) and for those groups especially at risk for elevated blood pressure, such as women (Alexander et al., 1996), the elderly (Schneider et al., 1995), African Americans (Barnes et al., 2004; Schneider et al., 1995, and adolescents with high normal blood pressure (Barnes et al., 2001; Barnes et al., 2004). Before excluding behavioral stress-reduction approaches as a recommendation for treatment of high blood pressure, as was the case in the recent JNC report (2003), clinical outcomes of the various stress-reduction techniques should be evaluated individually in order to not overlook any promising methods. http://campus.lakeforest.edu/kelley/bovee-2006.pdf
A83: Health | B83: Physiological | C83: Cardiovascular | D83: American Heart Association Statement, Reduced Hypertension | F83: 2013 | G83: s | H83: Brook RD, Appel LJ, Rubenfire M, Ogedegbe G, Bisognano JD, Elliott WJ, Fuchs F, Hughes JW, Lackland DT, Staffileno BA, Townsend RR, Rajagopalan S. Beyond medications and diet: alternative approaches to lowering blood pressure. A scientific statement from the American Heart Association. Hypertension 2013 61(6): 1360-1383 According to the American Heart Association, the Transcendental Meditation technique is the only meditation practice that has been shown to lower blood pressure. http://hyper.ahajournals.org/content/61/6/1360.full This scientific statement* reports, “Because of many negative studies or mixed results and a paucity of available trials, all other meditation techniques (including MBSR) received a 'Class III, no benefit, Level of Evidence C' recommendation. Thus, other meditation techniques are not recommended in clinical practice to lower BP at this time.” This AHA scientific statement also reported the finding that lower blood pressure through Transcendental Meditation practice is associated with substantially reduced rates of death, heart attack and stroke. This AHA statement concludes that alternative treatments that include the Transcendental Meditation technique are recommended for consideration in treatment plans for all individuals with blood pressure > 120/80 mm Hg. Abstract—Many antihypertensive medications and lifestyle changes are proven to reduce blood pressure. Over the past few decades, numerous additional modalities have been evaluated in regard to their potential blood pressure–lowering abilities. However, these nondietary, nondrug treatments, collectively called alternative approaches, have generally undergone fewer and less rigorous trials. This American Heart Association scientific statement aims to summarize the blood pressure–lowering efficacy of several alternative approaches and to provide a class of recommendation for their implementation in clinical practice based on the available level of evidence from the published literature. Among behavioral therapies, Transcendental Meditation (Class IIB, Level of Evidence B), other meditation techniques (Class III, Level of Evidence C), yoga (Class III, Level of Evidence C), other relaxation therapies (Class III, Level of Evidence B), and biofeedback approaches (Class IIB, Level of Evidence B) generally had modest, mixed, or no consistent evidence demonstrating their efficacy. Between the noninvasive procedures and devices evaluated, device-guided breathing (Class IIA, Level of Evidence B) had greater support than acupuncture (Class III, Level of Evidence B). Exercise-based regimens, including aerobic (Class I, Level of Evidence A), dynamic resistance (Class IIA, Level of Evidence B), and isometric handgrip (Class IIB, Level of Evidence C) modalities, had relatively stronger supporting evidence. It is the consensus of the writing group that it is reasonable for all individuals with blood pressure levels >120/80 mmHg to consider trials of alternative approaches as adjuvant methods to help lower blood pressure when clinically appropriate. A suggested management algorithm is provided, along with recommendations for prioritizing the use of the individual approaches in clinical practice based on their level of evidence for blood pressure lowering, risk-to-benefit ratio, potential ancillary health benefits, and practicality in a real-world setting. Finally, recommendations for futureresearchprioritiesareoutlined. (Hypertension.2013;61:00-00.)
A84: Health | B84: Psychological | C84: Affective | D84: PTSD | E84: RCT | F84: 1985 | G84: s | H84: Brooks JS, Scarano T. Transcendental Meditation in the treatment of post-Vietnam adjustment. Journal of Counseling and Development 1985 64:212-215 Over a three month period, people practicing the TM program showed clear-cut improvements in all aspects of PTSD syndrome, with significant decreases in depression, anxiety, insomnia, alcohol consumption, improvement in family problems, reduced severity of delayed stress syndrome and less emotional numbness, as well as greater ease in obtaining a job. By contrast the control group, who received standard treatment with psychotherapy showed no significant change on any measure.
A85: Social Behavior | B85: Sociological CP Vol 7 Pg4971 | C85: Productivity and Quality of Life | D85: Work-site Stress Reduction | E85: RCT | F85: 2005 | G85: s | H85: Broome JR, Orme-Johnson D, Schmidt-Wilk J. Worksite stress reduction through the Transcendental Meditation program. Journal of Social Behavior and Personality 2005 17(1):235-276 Employees who learned the Transcendental Meditation program showed decreased stress after six weeks and decreased blood pressure after 5.5 months, in contrast to employees practicing muscle relaxation. An experiment on stress reduction using the Transcendental Meditation (TM) technique and Progressive Muscle Relaxation (PMR) was conducted at a South African firm with 80 employees. Psychological stress decreased significantly over 5.5 months for the TM group (p<.0002) with 67% of the decrease in the first two weeks; for the PMR group (p<.03); and near significantly for on-site controls (p<.09). Blood pressure reduced significantly only for the TM group.
A86: Social Behavior | B86: Sociological | C86: Productivity and Quality of Life | D86: Maharishi Effect: World | F86: 2005 | G86: s | H86: Brown CL. Overcoming barriers to use of promising research among elite Middle East policy groups. Journal of Social Behavior and Personality 2005 17(1):489-546 This qualitative research examines how barriers to the use of new theoretical constructs in social science research might be overcome. Five groups of elite members of the Middle East policy community - peer reviewers, newspaper reporters, Congress people, non-governmental influentials and US diplomats - assessed a research study that explored a strategy for reducing conflict in the Middle East. That study was published in the Journal of Conflict Resolution (International Peace Project in the Middle East: The Effects of the Maharishi Technology of the Unified Field or IPPME) and found that when a critical mass of people used the Transcendental Meditation technique (e.g., crime and war intensity) were reduced in the surrounding population. Over half of each group reviewing the research rejected IPPME immediately without examining scientific merit. Stereotyping and prejudice were evident. Others, who assessed scientific quality independently of their organizational philosophies and practices and exhibited greater curiosity, were likelier to consider IPPME further.
A87: Health | B87: Physiological CPVol 2 Pg 804 | C87: Metabolic & Biochemical | D87: Increase in Serotonin - Rest and Fulfillment and Decrease in Fight or Flight response | F87: 1976 | G87: s | H87: Bujatti M, Riederer P. Serotonin, noradrenaline, dopamine metabolites in Transcendental Meditation. Journal of Neural Transmission 1976 39(3):257-267 Practitioners of the TM technique showed highly significant increases in levels of 5-HIAA (a serotonin metabolite) indicating an increase in rest and fulfillment and lower levels of VMA (an adrenaline and non-adrenaline metabolite) indicating a decrease in the fight or flight (arousal) response as compared to control subjects.
A88: Health | B88: Theoretical Papers Physiology and Health Hypercholesterolaemia CP Vol 7 Pg5107 | C88: Cardiovascular | D88: Reduced Cholesterol/Stress | F88: 1999 | G88: s | H88: Calderon R, Schneider R, Alexander CN, Myers H, Nidich S, Haney C. Stress, stress reduction and hypercholesterolemia in African Americans and whites: a review. Ethnicity and Disease 1999 9:451-462 This study supports previous and subsequent research showing significant improvement in cardiovascular health thru the practice of the TM technique. The authors review studies that the Transcendental Meditation Technique reduces stress and reduces risk factors for coronar heart disease, including hypercholersterolaemia.
A89: Social Behavior | B89: Psychological | C89: Rehabilitation | D89: At Risk Youth | F89: 2005 | G89: s | H89: Camelia CR, Hawkins, MA. The use of meditation with at-risk youth in the Netherlands Antilles. Caribbean Journal of Criminology and Social Psychology 2005 10(1/2):102-140 Despite the problems associated with the implementation of this study, some positive results were noted in the participants’ self reports and in the comments of the caretakers. The quantitative results are inconclusive and another, better-implemented study is required to test the hypothesis of this experiment. The qualitative results encourage further investigation of meditation as a treatment modality for at-risk youth.
A90: Mental Potential & Health & Social Behavior | B90: Psychological | C90: Rehabilitation | D90: Psychiatric | F90: 1975 | G90: s | H90: Candelent T, Candelent G. Teaching Transcendental Meditation in a psychiatric setting. Hospital and Community Psychiatry 1975 26(3):156-159 Psychiatric patients from a broad range of diagnostic categories experienced reduced anxiety, improvements in sleep patterns, and lessened overactive or impulsive behavior as a result of the practice of the Transcendental Meditation program. For two and a half years the authors taught the TM technique to psychiatric patients at the Institute of Living in Hartford, Connecticut.
A91: Health | B91: Physiological CP Vol7 Pg4722 | C91: Hypertension | D91: Atherosclerosis | E91: RCT | F91: 2000 | G91: s | H91: Castillo-Richmond A, Schneider RH, Alexander CN, Cook R, Myers H, Nidich S, Haney C, Rainforth M, Salerno J. Effects of stress reduction on carotid atherosclerosis in hypertensive African Americans. Stroke 2000 31(3):568-573 Hypertensive individuals randomly assigned to learn the Transcendental Meditation program, in contrast to a health edcuation control group, displayed significant reduction of carotid intima-media thickness over a six to nine month period. This randomized controlled trial of 60 African American subjects compared the effects of TM practice with a heart disease education group on carotid intima-media thickness, a validated surrogate measure for coronary and cerebral atherosclerosis. The results indicated a statistically significant decrease in carotid intima-media thickness, in the TM group by a 0.098mm (95% confidence interval [CI] [-0.198, 0.003mm]) compared with an increase of 0.054mm (95% CI [-0.05, 0.158mm]) in the control group (p=.038 for difference between groups), suggesting that TM may reduce carotid atherosclerosis in hypertensive African Americans. The literature indicates that changes of this magnitude predict a reduction in heart attacks (MI) by 11% (Salonen and Salonen 1993) and stroke by 7.7.% to 15% (O’Leary et al., by 1999)
A92: World Peace | B92: Sociological CPVol 5Pg 3188 | C92: Productivity and Quality of Life | D92: Maharishi Effect: World; Reduced Inflation and Unemployment | F92: 1987 | G92: s | H92: Cavanaugh KL. Time series analysis of US and Canadian inflation and unemployment: a test of a field theoretic hypothesis. Proceedings of the American Statistical Association, Business and Economics Statistics Section (pp.799-804). Alexandria, Virginia: American Statistical Association, 1987. Significant improvements shown in the Okun Misery Index (ie., decreased inflation and unemployment), greater strength and stability of the national currency, and improvements in other key economic indicators.Time series intervention analysis of monthly U.S. and Canadian trends (a misery index combining inflation and unemployment) showed improved economic conditions in months immediately after the number of participants exceeded the required number (1600) for the population of the U.S. and Canada.
A93: World Peace | B93: Sociological | C93: Quality of Life | D93: Maharishi Effect: Reduction in US Urban Murder Rates | F93: 2017 | G93: s | H93: Cavanaugh KL, Dillbeck MC. Field effects of consciousness and reduction in US urban murder rates: evaluation of a prospective quasi-experiment. Journal of Health and Environmental Research 2017 3(3-1):32-43. doi:10.11648/j.jher.s.2017030301.13 Creation of a sustainable society ideally should include promotion of an enhanced overall quality of life, including freedom from crime, violence, and other key indicators of social stress. This study is part of a comprehensive empirical evaluation of the results of a prospective four-year quasi-experiment that sought to reduce rates of homicide and violent crime as well as to improve other measures of the quality of life and public health in the United States. The current research tests the hypothesis that group practice of the Transcendental Meditation® (TM) and TM-Sidhi® program by a group of theoretically predicted size would be sufficient to reduce collective stress in the larger population, as reflected in decreased rates of homicide in a sample of 206 large U.S. urban areas. Time series regression analysis of monthly data for 2002–2010 using a broken-trend intervention model found significant reductions in trend for the urban homicide rate during the 2007–2010 intervention period (p = 1 x 10–13). Controlling for pre-intervention trends, seasonality, and autocorrelation, the estimated total reduction in homicide rate was 28.4% (7.1% annually). The practical significance of these findings is also indicated by an estimated 4,136 murders averted by the reduced trend in murder rate during the intervention. Diagnostic tests are satisfactory and indicate that the results are unlikely due to “spurious regression.” The mechanism for these macro-social effects is discussed in the light of possible alternative hypotheses.
A94: World Peace | B94: Sociological | C94: Productivity and Quality of Life | D94: Maharishi Effect: Redcution in US Urban Murder Rates | F94: 2017 | G94: s | H94: Cavanaugh KL, Dillbeck MC. The contribution of proposed field effects of consciousness to the prevention of US accidental fatalities: theory and empirical tests. Journal of Consciousness Studies 2017 24(1-2):53-86 This research tests the hypothesis that practice of a subjective procedure, the Transcendental Meditation® (TM) and TMSidhi programme®, by a group of a theoretically predicted size would be sufficient to increase conscious alertness in the larger population, as measured by reduced rates of motor vehicle fatalities and fatalities due to other accidents. Monthly data for 2002-2010 from a prospective quasi-experiment was analysed using intervention analysis to test for decreased trends in accident rates during the intervention period 2007-2010. Controlling for pre-intervention trends, seasonality, and autocorrelation, significant shifts in trend, at the predicted time and in the predicted direction, were evident in both series. These trend shifts indicated an average annual decline of 5.24% in motor vehicle fatalities controlling for vehicle miles travelled, and 3.38% in other accidental fatalities. The mechanism for these collective effects, apparently independent of behavioural interaction, is discussed in light of possible alternative hypotheses.
A95: World Peace | B95: Sociological | C95: Quality of Life | D95: Maharishi Effect, Reduction in Homicide | F95: 2022 | G95: s | H95: Cavanaugh KL, Dillbeck MC, Orme-Johnson DW. Evaluating a field theory of consciousness and social change: group practice of Transcendental Meditation and homicide trends. Studies in Asian Social Science 2022 8(1):1-32. doi.org/10.5430/sass.v8n1p1 Abstract This study outlines and empirically tests a field-theoretic view of consciousness and positive social change based onthe ancient Vedic tradition of knowledge from India (Veda means “knowledge” in Sanskrit) as brought to light by theVedic scholar and scientist of consciousness, Maharishi Mahesh Yogi. In contrast to most contemporary theories of mind and consciousness originating in the West, Maharishi’s Vedic science of consciousness posits the existence ofan interpersonal, nonlocalized dimension of consciousness that underlies both individual consciousness and the “collective consciousness” of society, or “national consciousness.” We review previous empirical tests in Cambodia, India, the Philippines (and other countries) of hypotheses derived from this field- theoretic view of consciousness. We then present new empirical results, which together with prior research, provide evidence for an interpersonal dimensioo to consciousness. Segmented-trend regression analysis of data from a prospective, 15-year U.S. national social experiment found support for the hypothesis that “field effects of consciousness” created by group practice of Transcendental Meditation® and its advanced technique, the TM-Sidhi® program, by theoretically predicted number of participants contributed to a reduction in social stress in national consciousness as indicated by improved monthly homicide trends during the study’s experimental period 2007-2011 (p < .0001). These results are consistent with significant reductions in crime and violence associated with group practice of the TM® and TM-Sidhi® program as reported in previous peer-reviewed research. This reduction was followed by a predicted subsequent increase in homicide trends 2012-2016 (p < .0001) after the group fell below the required size (approximately the √1% of the U.S.population).
A96: World Peace | B96: Sociological CPVol 5Pg 3207 | C96: Productivity and Quality of Life | D96: Maharishi Effect: Nation: Misery Index Improvement in Economic Quality of Life | F96: 1988 | G96: s | H96: Cavanaugh KL, King KD. Simultaneous transfer function analysis of Okun's misery index: improvement in the economic quality of life through Maharishi's Vedic science and technology of consciousness. Proceedings of the American Statistical Association, Business and Economics Statistics Section (pp.491-496). Alexandria, Virginia: American Statistical Association, 1988 Time series analysis of an economic “misery index” of U.S. inflation and unemployment rates demonstrated reduction in this index following periods of high numbers of participants in the group practice of the Transcendental Meditation and TM-Sidhi program at Maharishi International University, controlling for changes in key U.S. economic variables.
A97: World Peace | B97: Sociological CPVol 5Pg 3224 | C97: Productivity and Quality of Life | D97: Maharishi Effect: National Misery Index Improvement in Economic Quality of Life | F97: 1989 | G97: s | H97: Cavanaugh KL, King KD, Ertuna C. A multiple-input transfer function model of Okun’s misery index: an empirical test of the Maharishi Effect. Proceedings of the American Statistical Association, Business and Economics Statistics Section (pp.565-570), Alexandria, Virginia: American Statistical Association, 1989 Periods with large numbers in the group practice of the TM and TM-Sidhi program led to a marked reduction in an index of inflation and unemployment in the U.S., controlling for the effect of business cycle fluctuations as well as short and long term effects of other major economic variables.
A98: World Peace | B98: Sociological CPVol 5Pg 3240 | C98: Productivity and Quality of Life | D98: Maharishi Effect: Nation: Reduced Inflation and Unemployment | F98: 1989 | G98: s | H98: Cavanaugh KL, King KD, Titus BD. Consciousness and the quality of economic life: empirical research on the macroeconomic effects of the collective practice of Maharishi's Transcendental Meditation and TM-Sidhi program. Proceedings of the Midwest Management Society (pp.183-190). Chicago: Midwest Management Society, 1989 This paper reviews a series of studies that document improvements in the national economies of the US and Canada, as indicated by an index of decreased inflation and decreased unemployment, when the number of participants in Maharishi’s Transcendental Meditation and TM-Sidhi Program exceeded the square root of one percent of their national population. Significant improvements shown in the Okun Misery Index (ie., decreased inflation and unemployment), greater strength and stability of the national currency, and improvements in other key economic indicators.Time series intervention analysis of monthly U.S. and Canadian trends (a misery index combining inflation and unemployment) showed improved economic conditions in months immediately after the number of participants exceeded the required number (1600) for the population of the U.S. and Canada
A99: Mental Potential | B99: Psychological CP Vol 7 Pg4822 | C99: Development of Personality | D99: Self-Actualization | F99: 2005 | G99: s | H99: Chandler HM, Alexander CN, Heaton DP, Grant J. Transcendental Meditation and post-conventional self-development: a 10-year longitudinal study. Journal of Social Behavior and Personality 2005 17(1):93-122 Participants in the Transcendental Meditation Program showed significantly increased ego development over a 10-year period in contrast to matched control groups; they also displayed increased principled moral reasoning and intimacy, thus demonstrating development in cognitive, emotional, and ego functioning. This study explored the effects of the Transcendental Meditation (TM) technique on self-development as measured by Loevinger’s Washington University Sentence Completion Test of ego development, McAdam’s measure of intimacy motivation and Rest’s measure of principled moral reasoning. Ten-year longitudinal data indicated that TM participants increased markedly in ego development in contrast to three control groups matched for gender and age over the same time period (N=136, p<.0001). At posttest 38% (N=34) scored at or beyond the Autonomous level, versus 1% of controls (p=<.0001). TM participants also increased to very high levels of moral reasoning (p=.002) and intimacy (p=.02). The findings suggest that post-conventional development is stimulated by systematically transcending representational thought to experience pure consciousness.
A100: Mental Potential & Health | B100: Psychological | C100: Affective | D100: HIV Patients: Increased Vitality and Quality of Life | E100: RCT | F100: 2013 | G100: s | H100: Chhatre S, Metzger DS, Frank I, Boyer J, Thompson E, Nidich S, Montaner LJ, Jayadevappa R. Effects of behavioral stress reduction Transcendental Meditation intervention in persons with HIV. AIDS Care: Psychological and Socio-medical Aspects of AIDS/HIV 2013 25(10): 1291-1297. doi.org/10.1080/09540121.2013.764396 Stress is implicated in the pathogenesis and progression of HIV. The Transcendental Meditation technique is a behavioral stress reduction program that incorporates mind-body approach, and has demonstrated effectiveness in improving outcomes via stress reduction. We evaluated the feasibility of implementing Transcendental Meditation and its effects on outcomes in persons with HIV. In this community based single blinded Phase-I, randomized controlled trial, outcomes (psychological and physiological stress, immune activation, generic and HIV-specific health related quality of life, depression and quality of well-being) were assessed at baseline and at six months, and were compared using parametric and non-parametric tests. Twenty two persons with HIV were equally randomized to Transcendental Meditation intervention or healthy eating (HE) education control group. Retention was 100% in Transcendental Meditation group and 91% in healthy eating control group. The Transcendental Meditation group exhibited significant improvement in vitality. Significant between group differences were observed for generic and HIV-specific health related quality of life. . Small sample size may possibly limit the ability to observe significant differences in some outcomes. Transcendental Meditation stress reduction intervention in community dwelling adults with HIV is viable and can enhance health related quality of life. Further research with large sample and longer follow-up is needed to validate our results.
A101: Mental Potential | B101: Psychological CPVol5 Pg3150 | C101: Development of Personality | D101: Family Life | F101: 1987 | G101: s | H101: Chen ME. A comparative study of dimensions of healthy functioning between families practicing the TM program for five years or for less than a year. Journal of Holistic Nursing 1987 5(1):6-10 Families participating in the Transcendental Meditation program for at least five years were found to be more psychologically healthy than families who had just begun the practice, indicating development of more ideal family life.
...

Sheet Sleep Studies
A1: TM Research on Sleep / Insomnia
A2: Studies from Sheet1 where sleep or insomnia is an explicit outcome. Rows link back to Sheet1.
A4: Source Row | B4: Year | C4: Design | D4: Sleep-Related Results | E4: General Topic | F4: Specialty Area | G4: Full Citation & Abstract
A5: 435 | B5: ='All Research'!F435 -> 2021 | C5: =IF('All Research'!E435="","Observational",'All Research'!E435) -> RCT | D5: ='All Research'!D435 -> Reduced Emotional Distress, Anger, Fatigue Improved Academic Achievement, Quality of Sleep, Well Being | E5: ='All Research'!A435 -> Health & Mental Potential | F5: ='All Research'!C435 -> Affective | G5: ='All Research'!H435 -> Valosek L, Nidich S, Grant J, Peterson M, Nidich R. Effect of meditation on psychological stress and academic achievement in high school students: a randomized controlled study. Education 2021 141(4):192-200 The results of this randomized controlled study of ninth-grade students indicated significant reductions in the meditation group compared to silent reading controls in overall emotional distress, anger, and fatigue, and improvement in English language arts academic achievement and quality of sleep. These findings indicate the value of implementing TM to improve emotional wellbeing and academic performance in high school students. Analysis of covariance indicated that practice of meditation compared to controls significantly decreased psychological distress, as measured by SDQ emotional symptoms (F(1, 79)=4.90, p=.030), and anger (F(1, 80)=5.11, p=.027). The reduction in anxiety was in the expected direction but was not statistically significant F(1, 78)=0.46, p=.499).There was a significant improvement in the quality of sleep in the meditation group compared to controls (F(1, 79)=6.40, p=.013) and a marginally significant reduction in fatigue F(1, 80)=3.08, p=.082. (See Table 2.) Improvement was found in English Language Arts (ELA) academic achievement from prior year for the meditation group compared to controls (F(1, 66)=3.18, p=.079). Subgroup analysis of students who were below proficiency at baseline (n=37) indicated that 69% of the meditation students (11 out of 16) improved at least one performance level at post test compared to 33% of the control students (7 out of 21; [chi square]=4.56, p=.033). Change in attendance was also in the positive direction for the meditation group but did not reach statistical significance compared to controls (F(1, 81)=1.96, p=.166). Results of this study in ninth-grade students indicated significant reductions in psychological stress factors, decreased fatigue, improved quality of sleep, and increased academic achievement. This study builds upon previous research with school students (Nidich et al., 2011; Wendt et al., 2015; Valosek et 2018) while employing a randomized controlled design. The results are consistent with a large randomized study with college students, showing reduced psychological distress factors in those practicing TM compared to wait-list controls.
A6: 51 | B6: ='All Research'!F51 -> 2021 | C6: Pilot | D6: ='All Research'!D51 -> Reduced Insomnia, Anxiety Depression,Stress | E6: ='All Research'!A51 -> Health | F6: ='All Research'!C51 -> Affective | G6: ='All Research'!H51 -> Azizoddin DR, Kvaternik N, Beck M, Zhou G, Hasdianda MA, Jones N, Johnsky L, Im D, Chai PR, Boyer, EW. Heal the Healers: a pilot study evaluating the feasibility, acceptability, and exploratory efficacy of a Transcendental Meditation intervention for emergency clinicians during the coronavirus disease 2019 pandemic. Journal of the American College of Emergency Physicians Open 2021 2(6):e12619.doi.org/10.1002/emp2.12619 Abstract Objective: Emergency clinicians face elevated rates of burnout that result in poor outcomes for clinicians, patients, and health systems. The objective of this single-arm pilot study was to evaluate the feasibility of a Transcendental Meditation (TM) intervention for emergency clinicians during the coronavirus disease 2019 (COVID-19) pandemic and to explore the potential effectiveness in improving burnout, sleep, and psychological health. Methods: Emergency clinicians (physicians, nurses, and physician-assistants) from 2 urban hospitals were recruited to participate in TM instruction (8 individual or group in-person and remote sessions) for 3 months. Session attendance was the primary feasibility outcome (prespecified as attending 6/8 sessions), and burnout was the primary clinical outcome. Participant-reported measures of feasibility and validated measures of burnout, depression, anxiety, sleep disturbance, and stress were collected at baseline and the 1-month and 3-month follow-ups. Descriptive statistics and linear mixed effects models were used. Results: Of the 14 physicians (46%), 7 nurses (22%), and 10 physician-assistants (32%) who participated, 61% were female (n = 19/32). TM training and at-home meditation practice was feasible for clinicians as 90.6% (n = 29/32) attended 6/8 training sessions and 80.6% self-reported meditating at least once a day on average.Participants demonstrated significant reductions in burnout (P < .05; effect sizes, Cohen’s d = 0.43–0.45) and in symptoms of depression, anxiety, stress, and sleep disturbance (P values < .001; Cohen’s d = 0.70–0.87).
A7: 289 | B7: ='All Research'!F289 -> 2023 | C7: =IF('All Research'!E289="","Observational",'All Research'!E289) -> Observational | D7: ='All Research'!D289 -> Increased Clarity, Focus, Resilience, Energy, Stamina, Efficiency, Memory, Learning, Recall, Quality Sleep, Productive Time, Reduced Anxiety, | E7: ='All Research'!A289 -> Mental Potential Health | F7: ='All Research'!C289 -> Affective & Cognitive | G7: ='All Research'!H289 -> Nader T, Carroll RJ, Travis FW, Bray JB, Gruener G, Rothenberg S, Brown DH, Brown CL. A larger lens: medical students benefit from consciousness-based self-care. In ﻿AK Maheshwari (ed), Consciousness-Based Leadership and Management, Volume 2, Chapter 2 (pp 13-46), 2023. Palgrave Studies in Workplace Spirituality and Fulfillment. doi.org/10.1007/978-3-031-05839-4_2 Summary of Findings Three major benefits of regular TM practice were observed in these data: Students found that their most pressing needs—stress and anxiety reduction—were relieved with the TM technique. Students reported multiple positive benefits relating to many facets of their health and well-being, including: Greater mental clarity and improved focus Increased resilience, energy, stamina and efficiency Increased confidence, sense of control and adaptability Increased emotional stability, compassion, and empathy Improved memory, recall, learning and ability to synthesize Improved sleep and relief from physical symptoms of anxiety Improved relationships and teamwork With regular practice of the TM technique, the students gained additional productive time daily.
A8: 34 | B8: ='All Research'!F34 -> 1993 | C8: =IF('All Research'!E34="","Observational",'All Research'!E34) -> Observational | D8: ='All Research'!D34 -> Decreased Insomnia Workplace Less Stress, Reduced Cigarettes and Hard Liquor | E8: ='All Research'!A34 -> Health & Social Behavior | F8: ='All Research'!C34 -> Productivity and Quality of Life Dev of Personality | G8: ='All Research'!H34 -> Alexander CN, Swanson GC, Rainforth MV, Carlisle TW, Todd CC, Oates RM. Effects of the Transcendental Meditation program on stress reduction, health, and employee development: a prospective study in two occupational settings. Anxiety, Stress, and Coping 1993 6:245-262 This research study found that executives and employees who learned and regularly practiced theTranscendental Meditation program, in contrast to other employees from the same worksites, showed increased employee effectiveness, increased job satisfaction, improved personal and work relationships, reduced job worry and tension, reduced trait anxiety, decreased insomnia and decreased fatigue, reduced cigarette and hard liquor use, improved health and greater calm (lower skin conductance during task performance. The groups of participants in the Transcendental Meditation program also showed, in contrast to controls, improvement on three components found to underlie each of these measures, - increased occupational coherence, increased physiological settledness, and increased satisfaction with professional and personal life. This study examined health, stress and employee development in two settings in the automotive industry; a large manufacturing plant of a Fortune 100 company and a small sales distribution company. Employees who learned the TM technique showed significantly greater improvements on a wide variety of measures, including: reduced physiological arousal; decreases in anxiety, job tension, insomnia and fatigue; reduced consumption of cigarettes and hard liquor; and improved general health.
A9: 201 | B9: ='All Research'!F201 -> 1990 | C9: =IF('All Research'!E201="","Observational",'All Research'!E201) -> Observational | D9: ='All Research'!D201 -> Decreased Insomnia, Decreased Cigarettes, Increased Health of Industrial Workers | E9: ='All Research'!A201 -> Health | F9: ='All Research'!C201 -> Productivity and Quality of Life | G9: ='All Research'!H201 -> Haratani T, Hemmi T. Effects of Transcendental Meditation on health behavior of industrial workers. Japanese Journal of Public Health 1990 37:729 Industrial workers who learned the Transcendental Meditation program, in contrast to control employees, showed improved sleep quality, and decreased cigarette consumption. This study was conducted to assess the effect of the Transcendental Meditation program on worker’s health and behavior. Surveys were conducted before and after the introduction of the TM program. 427 TM participants and 308 controls who did not begin the practice in terms of health and behavior. The group who learned the TM program showed reduced time to fall asleep, less awakening during sleep, decrease in habitual smoking and fewer cigarettes smoked.
A10: 202 | B10: ='All Research'!F202 -> 1990 | C10: =IF('All Research'!E202="","Observational",'All Research'!E202) -> Observational | D10: ='All Research'!D202 -> Decreased Insomnia, Decreased Cigarettes, Increased Mental Health of Industrial Workers | E10: ='All Research'!A202 -> Health Social Behavior | F10: ='All Research'!C202 -> Productivity and Quality of Life | G10: ='All Research'!H202 -> Haratani T, Hemmi T. Effects of Transcendental Meditation on mental health of industrial workers. Japanese Journal of Industrial Health 1990 32:656 Takashi Haratani This was a five month study conducted by the researchers at Japan’s National Institute of Industrial Health. (A branch of the Japanese Ministry of Labor) industrial employees practicing the TM technique showed increased emotional stability, reduced anxiety, decreased tendency to neurosis and reduced insomnia and smoking compared to controls. Improvement in General Physical and Mental Well-Being in Industrial Workers: Decreased Physical Complaints; Decreased Impulsive Tendency; Reduced Emotional Instability. Overall, employees practicing TM improved significantly on 10 out of 14 mental health scales, whereas controls improved on only one.
A11: 15 | B11: ='All Research'!F15 -> 1978 | C11: =IF('All Research'!E15="","Observational",'All Research'!E15) -> Observational | D11: ='All Research'!D15 -> Reduced Insomnia TM in Corrections | E11: ='All Research'!A15 -> Social Behavior | F11: ='All Research'!C15 -> Rehabilitation | G11: ='All Research'!H15 -> Abrams AI, Siegel LM. The Transcendental Meditation program and rehabilitation at Folsom State Prison: a cross-validation study. Criminal Justice and Behavior 1978 5(1):3-20 The Transcendental Meditation program in a maximum security prison was studied via cross-validation design. Significant differences were found between the Transcendental Meditation and control groups across all the inventories, indicating reduction in anxiety, neuroticism, hostility, insomnia, fewer behavior infractions, decreased resentment; decreased negativism decreased irritability; improved sleep patterns (decreased time to fall asleep, decreased awakenings per night, improved quality of sleep).
A12: 271 | B12: ='All Research'!F271 -> 1977 | C12: =IF('All Research'!E271="","Observational",'All Research'!E271) -> Observational | D12: ='All Research'!D271 -> Decreased Insomnia, Reduced Use of Tranquilizers, Reduced Stress | E12: ='All Research'!A271 -> Mental Potential & Health | F12: ='All Research'!C271 -> Development of Personality | G12: ='All Research'!H271 -> Ljunggren G. The influence of Transcendental Meditation on neuroticism, use of drugs and insomnia. Lakartidningen 1977 74(47):4212-4214 Improvements in neuroticism and insomnia, and reduced use of tranquilizers were found to result from three months’ practice of the Transcendental Meditation technique. These findings indicate a relief from stress and increased psychological balance.

Sheet Alle Forschung
A1: MIT FREUNDLICHER GENEHMIGUNG DER GLOBAL MOTHER DIVINE ORGANIZATION® | H1: Forschungspublikationen zu
A2: Anfragen bitte per E-Mail an: tmresearchspreadsheet@tm-women.org | H2: Transzendentale Meditation® und TM-Sidhi-Programme®
H3: Bibliografie 1970–2026∗
H4: Diese Tabelle (Datenbank), erstellt von Jean Tobin von der Global Mother Divine Organization, fasst Zusammenfassungen, Abstracts und Daten zu Studiendesign und Ergebnissen von 485 Arbeiten zusammen, die in begutachteten Fachzeitschriften oder anderen unabhängigen, redaktionell betreuten wissenschaftlichen Publikationen veröffentlicht wurden. Die meisten dieser Arbeiten berichten über Originalstudien oder Forschungsübersichten; eine kleine Anzahl liefert wichtige Kommentare oder Klarstellungen zu bestimmten Studien, einschließlich Antworten auf Kritiken. Einige wenige Studien untersuchen einen umfassenden multimodalen Gesundheitsansatz, der die Transzendentale Meditation® einschließt. Transcendental Meditation®, TM® und TM-Sidhi® sind geschützte Marken und werden in den USA unter Lizenz oder mit Genehmigung verwendet. *Bibliografie der Forschungspublikationen zur Transzendentalen Meditation®, zusammengestellt von Dr. Roger Chalmers MRCP(UK) MRCGP DRCOG
H6: Spalte A: Allgemeines Thema: Gesundheit, geistiges Potenzial, Sozialverhalten, Weltfrieden
H7: Spalte B: Fachrichtung und Verweis auf gesammelte Arbeiten (falls zutreffend): physiologisch, psychologisch, soziologisch
H8: Spalte C: Fachgebiet: akademische Leistung, affektiv, biochemisch, kardiovaskulär, kognitiv, Persönlichkeitsentwicklung, EEG, elektrophysiologisch, Bildung, elektrophysiologisch, Gesundheit, Intelligenz, Lernen, metabolisch, Motorik und Wahrnehmung, physiologische Effizienz und Stabilität, Produktivität und Lebensqualität, Rehabilitation, Forschungsübersicht
H9: Spalte D: Spezifische Ergebnisse
H10: Spalte E: Randomisierte kontrollierte Studie / Meta-Analyse
H11: Spalte F: Erscheinungsjahr
H12: Spalte G: s = Zusammenfassung vorhanden
H13: Spalte H: Quellenangabe/Abstract/Zusammenfassung
A14: ALLGEMEINES THEMA | B14: FACHRICHTUNG und Verweis auf gesammelte Arbeiten | C14: FACHGEBIET | D14: SPEZIFISCHE ERGEBNISSE | E14: RCT /META | F14: JAHR
A15: Sozialverhalten | B15: Soziologisch CPVol 3Pg 2093 | C15: Rehabilitation | D15: Verringerte Insomnie – TM im Strafvollzug | F15: 1978 | G15: s | H15: Abrams AI, Siegel LM. The Transcendental Meditation program and rehabilitation at Folsom State Prison: a cross-validation study. Criminal Justice and Behavior 1978 5(1):3-20. Das Programm der Transzendentalen Meditation wurde in einem Hochsicherheitsgefängnis mittels eines Kreuzvalidierungsdesigns untersucht. Zwischen der Gruppe der Transzendentalen Meditation und der Kontrollgruppe wurden über alle Inventare hinweg signifikante Unterschiede festgestellt, die auf eine Verringerung von Angst, Neurotizismus, Feindseligkeit und Insomnie, weniger Verhaltensverstöße, verringerten Groll, verringerten Negativismus und verringerte Reizbarkeit sowie verbesserte Schlafmuster (verkürzte Einschlafzeit, weniger nächtliches Erwachen, verbesserte Schlafqualität) hinwiesen.
A16: Sozialverhalten | B16: Soziologisch CPVol 3Pg 2104 | C16: Rehabilitation | D16: TM im Strafvollzug | F16: 1979 | G16: s | H16: Abrams AI, Siegel LM. Transcendental Meditation and rehabilitation at Folsom Prison: response to a critique. Criminal Justice and Behavior 1979 6(1):13-21. Die im vorangegangenen Beitrag berichteten Vorteile der Transzendentalen Meditation erwiesen sich als nicht auf einen Selektionsbias oder eine Tendenz der Probanden zu sozial erwünschten, unwahren Antworten zurückführbar. Der Artikel antwortet auf den Einwand, die Befunde von Abrams und Siegel zum TM-Programm im Folsom State Prison seien auf Rosenthal-Versuchsleitereffekte zurückzuführen und die Daten seien von den Autoren allzu sparsam interpretiert worden. Die Autoren wiesen darauf hin, dass Rosenthal-Effekte nicht derart allgegenwärtig sind, dass vielversprechende Behandlungen in jedem denkbaren Fall abgetan werden sollten. Zudem zeigen die Daten der EPI-Lügenskala, dass die Behandlung die ohnehin geringe Neigung der Insassen zu sozial erwünschten, unwahren Antworten eher noch verringerte. In einer Meta-Analyse der Daten fanden sich keine konsistenten Zusammenhänge zwischen den Werten der Lügenskala und den Kriteriumsvariablen. Abschließend wurde die potenzielle Kosteneffektivität des Programms, die vom Kritiker infrage gestellt worden war, durch eine Analyse vorläufiger Rückfallquoten entlassener Teilnehmer gestützt.
A17: Gesundheit | B17: Physiologisch | C17: Kardiovaskulär | D17: Verringerter Bluthochdruck | F17: 1981 | G17: s | H17: Agarwal BL, Kharbanda A. Effect of transcendental meditation on mild and moderate hypertension. Journal of the Association of Physicians of India 1981 29:591-596. Bei Probanden mit leichtem und mittelschwerem Bluthochdruck wurden nach sechsmonatiger Praxis der Technik der Transzendentalen Meditation Senkungen des systolischen und diastolischen Blutdrucks festgestellt. Es wird nahegelegt, dass die Transzendentale Meditation in solchen Fällen als primäre Behandlung eingesetzt werden kann. Die Senkung des hohen Blutdrucks ist von großer Bedeutung für die Prävention von Herz-Kreislauf-Erkrankungen. Sechzehn Patienten mit leichter bis mittelschwerer essenzieller Hypertonie absolvierten ein sorgfältig überwachtes Programm der Transzendentalen Meditation (TM). Nach sechs Monaten kam es zu hochsignifikanten Senkungen des mittleren systolischen, diastolischen und arteriellen Mitteldrucks um 16,75, 9,81 bzw. 12,12. Zehn (62,5 %) der 16 Patienten galten als zufriedenstellend ansprechend, da sie eine Senkung des arteriellen Mitteldrucks um 15 mmHg oder mehr oder einen diastolischen Blutdruck von weniger als 90 mmHg zeigten. Die Ergebnisse sind mit einer medikamentösen Behandlung vergleichbar. Der größte Teil der Drucksenkung erfolgte in den ersten beiden Monaten. Nahezu alle Probanden berichteten von einem Gefühl des Wohlbefindens.
A18: Geistiges Potenzial | B18: Psychologisch: Übersicht CPVol 6 Pg 4385 | C18: Forschungsübersicht | D18: Übersicht der Wirkungen auf Individuum & Gesellschaft | F18: 1994 | G18: s | H18: Alexander CN. Transcendental Meditation. In RJ Corsini (ed.), Encyclopedia of Psychology (pp.5465-5466). New York: Wiley Interscience, 1994. Dieser Beitrag bietet eine Einführung in das Programm der Transzendentalen Meditation und die wichtigsten wissenschaftlichen Forschungsergebnisse zu seinen Wirkungen für das Individuum und die Gesellschaft.
A19: Geistiges Potenzial & Gesundheit | B19: Psychologisch: Übersicht CPVol5 Pg3399 | C19: Persönlichkeitsentwicklung | D19: TC | F19: 1986 | G19: s | H19: Alexander CN, Cranson RW, Boyer RW, Orme-Johnson DW. Transcendental Consciousness: a fourth state of consciousness beyond sleep, dreaming, and waking. In J Gackenbach (ed.), Sleep and Dreams: A Sourcebook (pp.282-312). New York: Garland Publishing, 1986. Es wird physiologische Forschung besprochen, die darauf hinweist, dass das transzendentale Bewusstsein ein einzigartiger vierter Hauptbewusstseinszustand ist.
A20: Geistiges Potenzial | B20: Psychologisch CP Vol5 Pg3411 | C20: Persönlichkeitsentwicklung | D20: TC+ | F20: 1990 | G20: s | H20: Alexander CN, Davies JL, Dixon CA, Dillbeck MC, Oetzel RM, Drucker SM, Muehlman JM, Orme-Johnson DW. Growth of higher stages of consciousness: Maharishi’s Vedic psychology of human development. In CN Alexander, EJ Langer (eds), Higher Stages of Human Development: Perspectives on Adult Growth (pp.286-341). New York: Oxford University Press, 1990. Die Autoren beschreiben, wie Theorie und Forschung in Maharishis Vedischer Psychologie das Bestreben der Psychologie erfüllen, die gesamte Bandbreite der menschlichen Entwicklung zu verstehen und zu fördern. Sind die vorgeschlagenen postformalen Stufen wirklich qualitativ von den formalen Operationen verschieden? Kramer (1983) vertritt die Ansicht, dass echte postformale Stufen drei Kriterien struktureller Veränderung erfüllen sollten: (1) größere Abstraktion des Denkens als bei den formalen Operationen, (2) hierarchische Integration der formalen Operationen und (3) ein umfassenderes Gleichgewicht (siehe Piaget, 1971a; Inhelder & Piaget, 1958). Wir werden die in diesem Band vorgeschlagenen postformalen Theorien kurz im Hinblick auf diese Kriterien untersuchen. Viele der Autoren, die postformale Stufen abgrenzen, stimmen in mehreren ihrer Hauptmerkmale überein, und es wurde vorgeschlagen (z. B. von Richards & Commons), dass die Übereinstimmung zwischen diesen Beschreibungen die Universalität der zugrunde liegenden beschriebenen Stufen widerspiegeln könnte. Es muss jedoch noch gezeigt werden, dass eine Person, die die Entwicklungskriterien für eine vorgeschlagene Stufe erfüllt, notwendigerweise auch die Merkmale ausdrückt, die zu den entsprechenden Stufen der anderen Theoretiker gehören. Geht beispielsweise die Fähigkeit, auf der Ebene des abstrakten Denkens über Systeme von Systemen zu urteilen, notwendigerweise mit einer stärkeren affektiven und Selbst-Integration einher? Diese Frage verspricht, wie viele andere, die durch die weitreichende Theoriebildung in diesem Band aufgeworfen werden, neue Richtungen und Ebenen der Entwicklungsforschung anzuregen. Eine zusammenfassende Verallgemeinerung lässt sich mit Sicherheit treffen: Praktisch alle Beitragenden stimmen darin überein, dass ein Verständnis der Adoleszenzentwicklung keine ausreichende Grundlage bietet, um die Breite, Tiefe und Reichhaltigkeit der potenziellen Entwicklung im Erwachsenenalter zu erfassen. Weitere konzeptionelle Klärung und Forschung zur Natur der Entwicklung jenseits der formalen Operationen sollte zu einer erheblichen Revision unseres Verständnisses der Möglichkeiten wahrhaft „reifer“ Formen menschlichen Wachstums führen. Letztlich wird die Art und Weise, wie wir den Endpunkt der Entwicklung begreifen, nicht nur die Richtung unserer Forschungsagenden beeinflussen, sondern auch unsere eigene persönliche Entwicklung entweder einschränken oder fördern.
A21: Geistiges Potenzial | B21: Psychologisch | C21: Persönlichkeitsentwicklung | D21: Entwicklung im Erwachsenenalter | F21: 1990 | G21: s | H21: Alexander CN, Drucker SM, Langer EJ. Major issues in the exploration of adult growth. In CN Alexander, EJ Langer (eds), Higher Stages of Human Development: Perspectives on Adult Growth (pp.3-32). New York: Oxford University Press, 1990. Was sind die höchstmöglichen Formen der menschlichen Entwicklung? Die eigene Vorstellung vom Endpunkt der Entwicklung ist grundlegend, denn sie enthält die Annahmen über Richtung, Möglichkeiten und Dynamik des menschlichen Wachstums. Zudem werden alle vorangehenden Entwicklungsstufen als fortschreitende Annäherungen an dieses Ziel betrachtet. Die Beitragenden dieses Bandes wurden gebeten, sich mit dieser grundlegenden Frage des Endpunkts zu befassen. Die Beantwortung dieser Frage erfordert im Allgemeinen die Betrachtung dreier zusammenhängender Fragen: Verläuft die Entwicklung zum Endpunkt hin über qualitativ verschiedene Stufen? Welche Mechanismen liegen dieser Entwicklung zugrunde? Welche wesentlichen Bereiche werden entwickelt (z. B. Kognition und Affekt), und wie hängen sie zusammen? Auf der Grundlage neuerer Theorie und Forschung bieten die Kapitel dieses Buches erweiterte Perspektiven auf diese wichtigen Fragen.
A22: Geistiges Potenzial | B22: Psychologisch | C22: Bildung | D22: Management | F22: 1990 | G22: s | H22: Alexander CN, Heaton DP, Chandler HM. Promoting adult psychological development: implications for management education. Human Resource Management 1990 2:133-137. Dieser Beitrag befasst sich mit der entscheidenden Frage, was die Managementausbildung tun kann, um die persönlichen Eigenschaften zu entwickeln, die zur Erfüllung des Bedarfs an Führungskräften erforderlich sind. Wir argumentieren, dass 1) die psychologische Entwicklung der Ausführung der Managementaufgaben zugrunde liegt und 2) die psychologische Entwicklung durch geeignete Technologien gefördert werden kann; daher 3) kann eine solche Technologie eingesetzt werden, um Führungskräfte und darüber hinaus zu entwickeln. In Längsschnittstudien zur Technologie der Ich-Entwicklung erfuhr die Technik der Transzendentalen Meditation eine beispiellose Auflösung der Erstarrung der psychologischen Entwicklung im Erwachsenenalter. Eine weitere Anwendung dieser Technologie könnte die Entwicklung von Führungskräften für die Anforderungen des einundzwanzigsten Jahrhunderts erleichtern.
A23: Geistiges Potenzial | B23: Psychologisch CP Vol6 Pg4325 | C23: Persönlichkeitsentwicklung | D23: TC+ | F23: 1994 | G23: s | H23: Alexander CN, Heaton DP, Chandler HM. Advanced human development in the Vedic Psychology of Maharishi Mahesh Yogi: theory and research. In ME Miller, SR Cook-Greuter (eds), Transcendence and Mature Thought in Adulthood: The Further Reaches of Adult Development (pp.39-70). Lanham, Maryland: Rowman & Littlefield, 1994. Die Autoren beschreiben die Entwicklung höherer Bewusstseinszustände, wie sie von Maharishi Mahesh Yogi in seiner Vedischen Psychologie ans Licht gebracht wurde, und stellen dies zeitgenössischen Themen der kognitiven oder Selbstentwicklung gegenüber. Anschließend besprechen die Autoren Forschung, die außergewöhnlich hohe Werte in der Selbstentwicklung bei fortgeschrittenen Praktizierenden von Maharishis Transzendentaler Meditation und TM-Sidhi-Programm nachweist.
A24: Geistiges Potenzial | B24: Psychologisch | C24: Bildung | D24: Word of Wisdom | F24: 2005 | G24: s | H24: Alexander CN, Kurth SC, Travis F, Alexander VK. Effect of practice of the children’s Transcendental Meditation technique on cognitive stage development: acquisition and consolidation of conservation. Journal of Social Behavior and Personality 2005 17(1):21-46. Die Ergebnisse dieser Studie zur kognitiven Stufenentwicklung bei Kindern, die die Maharishi-Word-of-Wisdom-Technik praktizieren, sind bemerkenswert. Diese Befunde legen nahe, dass die Praxis der Word-of-Wisdom-Technik die Geschwindigkeit des Erwerbs und insbesondere der Konsolidierung der Erhaltung (conservation) in der Kindheit beschleunigen kann. Die Übergangsphase bei der Beherrschung der Konsolidierung der Erhaltung – die horizontale Décalage – war bei diesen Kindern erheblich verkürzt. Die Ergebnisse dieser Studie zeigen deutlich, dass die Praxis der Word-of-Wisdom-Technik bei Kindern positiv mit der Leistung bei einer Reihe von kognitiven Entwicklungsaufgaben zur Messung der Erhaltung zusammenhängt. Alle drei experimentellen Hypothesen wurden bestätigt. Erstens schienen die Kinder, die die Word-of-Wisdom-Technik praktizierten, den Erwerb von Erhaltungsfähigkeiten in einem früheren Alter zu beginnen als die Kontrollkinder. Zweitens zeigte ein signifikant größerer Anteil der Word-of-Wisdom-Gruppe eine vollständige Konsolidierung der Erhaltung, wie die vollständige Beherrschung der Erhaltungsreihe zeigte. Schließlich wiesen signifikant weniger der Word-of-Wisdom-Kinder eine horizontale Décalage auf, wie ein Übergangswert in der Erhaltungsreihe zeigte. Die Leistung der Kinder, die die Word-of-Wisdom-Technik praktizierten, deutet eher auf Phasenübergänge zwischen den Stufen als auf eine anhaltende zeitliche Verschiebung hin. Eine bemerkenswerte Implikation dieses Befundes der beschleunigten Konsolidierung ist, dass die Optimierung des natürlichen Wachstumsprozesses in der Kindheit durch die Praxis der Word-of-Wisdom-Technik zu einer erheblichen Verkürzung und in manchen Fällen möglicherweise zur Beseitigung der entwicklungsbedingten „Unregelmäßigkeit“ der horizontalen Décalage führen kann. Angesichts dessen, dass praktisch alle Kinder, die die Word-of-Wisdom-Technik praktizierten, im Alter von 5,08 Jahren vollständig erhaltend waren, und dass die vollständige Erhaltung typischerweise erst mit 11 oder 12 Jahren auftritt, würde die stärkstmögliche Interpretation dieser Daten nahelegen, dass die Praxis der Word-of-Wisdom-Technik die Konsolidierung der Erhaltung im Vergleich zur größeren Population um bis zu 5 bis 7 Jahre beschleunigen kann. Diese Querschnittsstudie untersuchte die kognitive Stufenentwicklung bei 47 Kindern, die die Word-of-Wisdom-Technik praktizierten, und bei 47 gematchten Kontrollkindern.
A25: Geistiges Potenzial | B25: Psychologisch | C25: Persönlichkeitsentwicklung | D25: TC+ | F25: 1990 | G25: s | H25: Alexander CN, Langer EJ (eds). Higher Stages of Human Development: Perspectives on Adult Growth. New York: Oxford University Press, 1990. Die Autoren beschreiben, wie Theorie und Forschung in Maharishis Vedischer Psychologie das Bestreben der Psychologie erfüllen, die gesamte Bandbreite der menschlichen Entwicklung zu verstehen und zu fördern. Diese Forschung liefert eindrucksvolle Belege dafür, dass Maharishis Programm der Transzendentalen Meditation die Entwicklung über vier wesentliche Entwicklungsperioden hinweg fördert. Diese Befunde stellen einen weithin vertretenen Grundsatz der Entwicklungspsychologie infrage, wonach die Qualität der direkten Interaktion mit der äußeren physischen oder sozialen Umwelt notwendigerweise der entscheidende Faktor für das kognitive Wachstum sei. In diesen Studien wurde weder eine externe Anreicherung der Umwelt noch ein Training mit testbezogenen Materialien oder auch nur mit verwandten Konzepten eingesetzt. Stattdessen ergab sich eine erhebliche Veränderung daraus, dass die Aufmerksamkeit systematisch nach innen auf intrinsisch tiefere Ebenen des Geistes und letztlich auf das reine Bewusstsein an ihrer Quelle gerichtet wurde. Unabhängig vom anfänglichen Entwicklungsniveau des Probanden (z. B. mitunter recht niedrig in den Gefängnisstichproben: Alexander, 1982) wurde die Entwicklungsgeschwindigkeit durch Erfahrungen des reinen Bewusstseins während der TM-Technik rasch beschleunigt. Auf Grundlage dieser Ergebnisse schließen die Autoren, dass der Prozess des Transzendierens durch das TM-Programm die Entwicklung über die von der zeitgenössischen Psychologie üblicherweise identifizierten Entwicklungsperioden hinweg fördert und diesen Wachstumsprozess auf die von Maharishis Vedischer Psychologie beschriebenen höheren Bewusstseinszustände ausdehnt. Sie schlagen vor, dass bei breiter Einführung dieser Entwicklungstechnologie im frühestmöglichen geeigneten Alter die Entwicklung nicht vorzeitig erstarren würde und das Wachstum zur vollen Erleuchtung als unvermeidliche Folge der normalen menschlichen Entwicklung erscheinen würde.
A26: Gesundheit | B26: Physiologisch CPVol 6 Pg3840 | C26: Gesundheit: Langlebigkeit | D26: Altern; verringerter Blutdruck, verbesserte kognitive Funktion und erhöhte Langlebigkeit | E26: RCT | F26: 1989 | G26: s | H26: Alexander CN, Langer EJ, Newman RI, Chandler HM, Davies JL. Transcendental Meditation, mindfulness, and longevity: an experimental study with the elderly. Journal of Personality and Social Psychology 1989 57(6):950-964. Eine sorgfältig kontrollierte randomisierte Studie an der Harvard University ergab, dass ältere Personen, die die Technik der Transzendentalen Meditation erlernten, signifikant größere Verbesserungen bei einer Vielzahl altersbezogener Aspekte der körperlichen und psychischen Gesundheit und des Wohlbefindens zeigten als Probanden, die andere Techniken erlernten, oder eine unbehandelte Kontrollgruppe. Insbesondere zeigten diejenigen, die ein Entspannungsverfahren erlernten, das die Technik der Transzendentalen Meditation nachzuahmen versuchte, bei keinem Maß eine Verbesserung. Eine klare Mehrheit der Probanden, die die TM-Technik praktizierten, bewertete ihre Technik als besonders nützlich und leicht auszuüben, im Gegensatz zu niedrigeren Bewertungen für die anderen Techniken. Am bemerkenswertesten war, dass nach drei Jahren alle, die die TM-Technik erlernt hatten, noch am Leben waren, im Gegensatz zu signifikant niedrigeren Überlebensraten für die anderen drei Gruppen und für die übrigen Bewohner der anderen Einrichtungen, in denen die Studie durchgeführt wurde. Vorteile für ältere Menschen als Nachweis einer Umkehr des Alterns: erhöhte Langlebigkeit (höhere Überlebensrate); Senkung des systolischen Blutdrucks auf idealere Werte; verbesserte psychische Gesundheit (Verbesserungen bei den Bewertungen der psychischen Gesundheit durch Pflegekräfte); erhöhte kognitive Flexibilität (verbale Aufgabe); erhöhte Lernfähigkeit (Paarassoziations-Lernaufgabe); Verbesserungen bei selbstberichteten Maßen der Verhaltensflexibilität und des Alterns (größere Fähigkeit, mit Unannehmlichkeiten umzugehen, verringertes Gefühl, alt zu sein); größeres Wohlbefinden (sich nach der Transzendentalen Meditation besser und entspannter fühlen; sich während der Transzendentalen Meditation besser fühlen; hohes Interesse an der Transzendentalen Meditation; und hohe Bewertungen des Werts der Transzendentalen Meditation).
A27: Sozialverhalten | B27: Soziologisch CP Vol 7 Pg4900 | C27: Rehabilitation | D27: TM im Strafvollzug: verringerte schizophrene Symptome, verringerte Aggression, verringerte Angst | F27: 2003 | G27: s | H27: Alexander CN, Orme-Johnson DW. Walpole study of the Transcendental Meditation program in maximum security prisoners II: longitudinal study of development and psychopathology. Journal of Offender Rehabilitation 2003 36(1-4):127-160. Gefängnisinsassen in Massachusetts, USA, die das Programm der Transzendentalen Meditation erlernten und über einen Zeitraum von 15 Monaten regelmäßig praktizierten, zeigten im Gegensatz zu Kontrollinsassen eine signifikant gesteigerte Ich-Entwicklung, verringerte Aggression, verringerte schizophrene Symptome und eine erhöhte Häufigkeit von Erfahrungen höheren Bewusstseins im Vergleich zu Mitgliedern mehrerer Kontrollgruppen. 271 Hochsicherheitshäftlinge nahmen entweder am Programm der Transzendentalen Meditation (TM), an Beratung, an Drogenrehabilitation oder an glaubensbasierten Gruppen teil. Nur regelmäßige Teilnehmer des TM-Programms veränderten sich signifikant. TM-Probanden zeigten signifikante Verringerungen der Aggression (p < ,05), insbesondere diejenigen, die mindestens zweimal pro Woche meditierten (p < ,005). Darüber hinaus zeigten sie verringerte schizophrene Symptome (p < ,05), verringerte Ängstlichkeit als Persönlichkeitsmerkmal (p < ,10, Trend) und eine erhöhte Häufigkeit postkonzeptueller Erfahrung höherer Bewusstseinszustände (p < ,01).
A28: Sozialverhalten | B28: Soziologisch CP Vol 7 Pg4923 | C28: Rehabilitation | D28: TM im Strafvollzug: verringerte Rückfallquote | F28: 2003 | G28: s | H28: Alexander CN, Rainforth MV, Frank PR, Grant JD, Von Stade C. Walpole study of the Transcendental Meditation program in maximum security prisoners III: reduced recidivism. Journal of Offender Rehabilitation 2003 36(1-4):161-180. Gefängnisinsassen in Massachusetts, USA, die während ihrer Haft das Programm der Transzendentalen Meditation erlernten, zeigten im Gegensatz zu Kontrollgruppen aus demselben Gefängnis eine signifikant geringere Rückkehr ins Gefängnis für 30 Tage oder länger sowie eine signifikant niedrigere Rate der erneuten Inhaftierung aufgrund neuer Festnahmen. Insassen, die die TM-Technik praktizierten, erfuhren eine Verringerung der Rückfallquote um 33 %, was statistisch signifikant war (p = ,042). Gesonderte Vergleiche zeigten, dass die TM-Gruppe zudem niedrigere Wiederinhaftierungsraten aufwies als jedes der vier anderen Programme, mit proportionalen Verringerungen der Rückfallquote von 29 % bis 42 % (p = ,007 bis ,073). Darüber hinaus wies die TM-Gruppe im Vergleich zu allen nicht meditierenden Probanden eine niedrigere Rate der erneuten Inhaftierung aufgrund neuer Verurteilungen (proportional 47 % niedriger; p = ,045) und eine proportional 27 % niedrigere Rate der erneuten Inhaftierung/eines Haftbefehls (p = ,069) auf. Das Muster der verringerten Rückfälligkeit für die Mitglieder des TM-Programms blieb in multiplen Regressionsanalysen bestehen, unter Kontrolle von Hintergrund- und Entlassungsvariablen (z. B. Bewährung vs. vollständige Entlassung, Entlassungseinrichtung, Drogenanamnese). Diese Befunde stehen im Einklang mit der These, dass die durch das TM-Programm bewirkte verringerte Psychopathologie und die beschleunigte psychologische Entwicklung für die Verringerung des kriminellen Verhaltens verantwortlich sind. In dieser Studie wurde eine Gruppe, die das TM-Programm erlernt hatte (N = 53), mit einer Kontrollgruppe (N = 233) von Insassen verglichen, die die TM-Technik nicht praktizierten.
A29: Geistiges Potenzial | B29: Psychologisch CP Vol6 Pg3966 | C29: Persönlichkeitsentwicklung | D29: Selbstverwirklichung | E29: Meta | F29: 1991 | G29: s | H29: Alexander CN, Rainforth MV, Gelderloos P. Transcendental Meditation, self-actualization, and psychological health: a conceptual overview and statistical meta-analysis. Journal of Social Behavior and Personality 1991 6(5):189-247. Diese Meta-Analyse aller Forschung zu den Wirkungen des TM-Programms auf die Selbstverwirklichung ergab im Vergleich zu anderen Techniken, dass das Programm der Transzendentalen Meditation die dreifache Effektstärke anderer Verfahren bei der Steigerung der Selbstverwirklichung und ihrer weiteren Komponenten (emotionale Reife, integrierte Sicht auf Selbst und Welt sowie ein widerstandsfähiges Selbstgefühl) aufwies. Es zeigte sich zudem, dass das Programm der Transzendentalen Meditation zu signifikanten Verbesserungen auf jeder der zwölf Skalen des gängigsten Tests zur Selbstverwirklichung führt. In einer statistischen Übersicht von 42 unabhängigen Forschungsergebnissen erwies sich das TM-Programm als dreimal so wirksam wie andere Meditations- und Entspannungsverfahren bei der Steigerung der Selbstverwirklichung – eines Gesamtmaßes für positive psychische Gesundheit und persönliche Entwicklung. Weitere Analysen ergaben, dass die Technik außergewöhnlich wirksam bei der Entwicklung dreier unabhängiger Komponenten dieser Dimension ist: emotionale Reife, ein widerstandsfähiges Selbstgefühl und eine positive, integrierte Sicht auf uns selbst und die Welt. Erhöhte Selbstverwirklichung durch Transzendentale Meditation im Gegensatz zu anderen Verfahren, wie durch Meta-Analyse nachgewiesen; Verbesserung der gemessenen Komponenten der Selbstverwirklichung: erhöhte Zeitkompetenz (Fähigkeit, in der Gegenwart zu leben; Fähigkeit, Vergangenheit, Gegenwart und Zukunft sinnvoll zu verbinden); erhöhte Innengeleitetheit (Unabhängigkeit; Selbstständigkeit); erhöhter selbstverwirklichender Wert (Vertreten der Werte selbstverwirklichter Menschen); erhöhte Existenzialität (Flexibilität in der Anwendung von Werten); erhöhte Spontaneität; erhöhte Selbstachtung; erhöhte Selbstakzeptanz; erhöhte konstruktive Sicht des Menschen (den Menschen als im Wesentlichen gut sehen); erhöhte Synergie (die Gegensätze des Lebens als sinnvoll verbunden sehen); erhöhte Akzeptanz von Gefühlen; erhöhte Fähigkeit zu intimem Kontakt (warme zwischenmenschliche Beziehungen); erhöhte emotionale Reife; erhöhte integrative Sicht auf Selbst und Welt; erhöhtes widerstandsfähiges Selbstgefühl.
A30: Gesundheit | B30: Physiologisch Übersicht CPVol 6 Pg 4255 | C30: Kardiovaskulär, Gesundheit, Rehabilitation, affektiv, Persönlichkeitsentwicklung | D30: Vergleich von Techniken: Übersicht über 4 Meta-Analysen | F30: 1994 | G30: s | H30: Alexander CN, Robinson P, Orme-Johnson DW, Schneider RH, Walton KG. The effects of Transcendental Meditation compared to other methods of relaxation in reducing risk factors, morbidity, and mortality. Homeostasis 1994 352:243-264. Dieser Beitrag bespricht vier Meta-Analysen, die die Überlegenheit des Programms der Transzendentalen Meditation gegenüber anderen Techniken beim Erzeugen tiefer Ruhe, bei der Verringerung von Angst, der Steigerung der Selbstverwirklichung und der Verringerung von Substanzmissbrauch (Zigaretten, Drogen, Alkohol) zeigen. Er bespricht außerdem einzelne gut kontrollierte Studien zu den vorteilhaften Wirkungen dieser Technik auf Bluthochdruck, Sterblichkeit, medizinische Versorgung und medizinische Kosten und erörtert physiologische Mechanismen für diese Wirkungen.
A31: Sozialverhalten | B31: Soziologisch CPVol 6Pg 4013 | C31: Rehabilitation | D31: Verringerter Substanzmissbrauch (Alkohol, Drogen und Zigaretten) | E31: Meta | F31: 1994 | G31: s | H31: Alexander CN, Robinson P, Rainforth MV. Treating and preventing alcohol, nicotine, and drug abuse through Transcendental Meditation: a review and statistical meta-analysis. Alcoholism Treatment Quarterly 1994 11(1/2):13-87. Dieser Beitrag stellt eine Meta-Analyse des Programms der Transzendentalen Meditation vor, die zeigt, dass Personen, die dieses Programm erlernen, eine signifikant stärkere Verringerung des Konsums illegaler Drogen, von Alkohol und Zigaretten aufweisen als Personen, die an Programmen zur Entspannung, Prävention oder Behandlung teilnehmen. Die Ergebnisse zeigten außerdem, dass die Abstinenz von illegalen Drogen, Alkohol und Zigaretten bei den Teilnehmern des TM-Programms über einen langen Zeitraum aufrechterhalten oder sogar gesteigert wurde, im Gegensatz zu hohen Rückfallquoten bei Standardbehandlungsprogrammen. Die Meta-Analyse zeigte zudem, dass Personen mit Substanzmissbrauchsproblemen, die das TM-Programm erlernten, im Vergleich zu Kontrollpersonen eine signifikant verbesserte psychische Gesundheit aufwiesen. Diese Meta-Analyse von 155 Studien ergab, dass das TM-Programm bei der Verringerung des Alkoholkonsums signifikant wirksamer war (d=0,55) als Entspannungstechniken, Beratung, Gruppendruck und DUI-Programme (die d-Werte reichten von 0,07 bis 0,33). Darüber hinaus ergab eine statistische Meta-Analyse, die 19 Studien zu den Wirkungen des TM-Programms zusammenfasste, dass die Technik erhebliche und hochsignifikante Verringerungen des Konsums von Alkohol, Zigaretten und illegalen Drogen bewirkte, mit größeren Effekten als andere Behandlungen, einschließlich Standardtherapien und anderer Techniken der Meditation und Entspannung. Über einen Zeitraum von 18–24 Monaten lag die Abstinenz beim TM-Programm zwischen 51 % und 89 %, verglichen mit 21 % bei guten herkömmlichen Substanzmissbrauchsprogrammen. Ergebnisse der integrativen Meta-Analyse: signifikant stärkere Verringerung des Konsums illegaler Drogen, von Alkohol und Zigaretten als bei Programmen zur Entspannung, Prävention oder Behandlung; Abstinenz von illegalen Drogen, Alkohol und Zigaretten langfristig aufrechterhalten oder gesteigert (Rückfallprävention); verbesserte psychische Gesundheit (verringerte negative Eigenschaften, verringerte Angst, verbesserte positive Eigenschaften) bei Personen mit Substanzmissbrauchsproblemen im Vergleich zu Kontrollpersonen. Jahrzehntelange Bemühungen in der Behandlung von Substanzmissbrauch haben keine umfassende Behandlungsstrategie hervorgebracht, die der multidimensionalen Natur der chemischen Abhängigkeit erfolgreich gerecht wird. Der vorliegende Beitrag vertritt die These, dass das Programm der Transzendentalen Meditation (TM) einen ganzheitlichen, natürlichen und wirksamen Ansatz bietet, der positiv auf eine Reihe von Faktoren – soziale, umweltbedingte, physiologische, psychologische und spirituelle – einwirkt, die das Suchtverhalten beeinflussen. Die Wirkungen der TM auf Rauchen, Trinken und den Konsum illegaler Drogen nehmen tendenziell mit der Zeit zu, was auf einen kumulativen Effekt regelmäßiger TM-Praxis hindeutet. Im Gegensatz dazu ist bekannt, dass die Erfolgsraten bei Standard-Drogenbehandlungen im Laufe der Zeit erheblich nachlassen. Bei Alkoholmissbrauch erzeugte die TM einen signifikant größeren Effekt als: (1) Bildungsprogramme zur Förderung der Widerstandsfähigkeit gegen Gruppendruck; (2) Präventionsbildungsprogramme zur Steigerung des Selbstwertgefühls und des Wissens über die Folgen von Drogen; (3) der Durchschnitt einer breiten Palette von DUI-Behandlungsprogrammen wie AA und therapeutischen Bewährungsprogrammen; und (4) der Durchschnitt anderer Entspannungsbehandlungsprogramme (einschließlich Biofeedback, Muskelentspannung, Stressmanagement-Training und anderer Formen der Meditation). Beim Tabakrauchen erzeugte die TM signifikant größere Effekte als: (1) Drogenpräventionsbildungsprogramme; (2) Beratungsprogramme zur Raucherentwöhnung; (3) Bibliotherapie; (4) pharmakologische Behandlungen der Nikotinsucht (einschließlich Nikotinersatzprogrammen und Clonidin-Therapie); und (5) „unkonventionelle“ Behandlungen (einschließlich Akupunktur, Hypnose, sensorischer Deprivation usw.). Bei illegalen Drogen (Cannabis, Halluzinogene und Betäubungsmittel) erzeugte die TM signifikant größere Effekte als: (1) Präventionsbildungsprogramme mit Bezug auf Gruppendruck; und (2) Präventionsbildungsprogramme zur Förderung des Selbstwertgefühls und des Wissens über Drogen.
A32: Geistiges Potenzial | B32: Psychologisch | C32: Affektiv | D32: Entspannung | F32: 1993 | H32: Alexander CN, Sands D. Meditation and relaxation. In FN McGill (ed.), McGill’s Survey of the Social Sciences: Psychology (pp.1499-1505). Pasadena, California: Salem Press, 1993
A33: Gesundheit | B33: Physiologisch | C33: Kardiovaskulär | D33: Verringerter Bluthochdruck und Altern/Geschlecht | E33: RCT | F33: 1996 | G33: s | H33: Alexander CN, Schneider RH, Staggers F, Sheppard W, Clayborne BM, Rainforth MV, Salerno J, Kondwani K, Smith S, Walton K, Egan B. Trial of stress reduction for hypertension in older African Americans: II. Sex and risk subgroup analysis. Hypertension 1996 28(2):228-237. Idealere Blutdruckwerte bei hypertensiven Probanden, die das Programm der Transzendentalen Meditation erlernten: Senkung des hohen systolischen und diastolischen Blutdrucks sowohl bei Männern als auch bei Frauen und sowohl bei Probanden mit hohem als auch mit niedrigem psychosozialem Stress; Senkung des hohen systolischen und diastolischen Blutdrucks unabhängig vom Wert bei fünf weiteren Risikomaßen für hohen Blutdruck, Adipositas, Alkoholkonsum, körperliche Inaktivität, Natrium-Kalium-Aufnahme über die Ernährung und einem Index aller kombinierten Risikofaktoren.
A34: Gesundheit & Sozialverhalten | B34: Soziologisch CPVol6 Pg 4056 | C34: Produktivität und Lebensqualität, Persönlichkeitsentwicklung | D34: Verringerte Insomnie, weniger Stress am Arbeitsplatz, reduzierter Konsum von Zigaretten und Spirituosen | F34: 1993 | G34: s | H34: Alexander CN, Swanson GC, Rainforth MV, Carlisle TW, Todd CC, Oates RM. Effects of the Transcendental Meditation program on stress reduction, health, and employee development: a prospective study in two occupational settings. Anxiety, Stress, and Coping 1993 6:245-262. Diese Forschungsstudie ergab, dass Führungskräfte und Mitarbeiter, die das Programm der Transzendentalen Meditation erlernten und regelmäßig praktizierten, im Vergleich zu anderen Mitarbeitern derselben Arbeitsstätten eine gesteigerte Mitarbeitereffektivität, höhere Arbeitszufriedenheit, verbesserte persönliche und berufliche Beziehungen, verringerte berufliche Sorgen und Anspannung, verringerte Ängstlichkeit als Persönlichkeitsmerkmal, verringerte Insomnie und verringerte Erschöpfung, reduzierten Konsum von Zigaretten und Spirituosen, verbesserte Gesundheit und größere Gelassenheit (geringere Hautleitfähigkeit während der Aufgabenausführung) aufwiesen. Die Gruppen der Teilnehmer am Programm der Transzendentalen Meditation zeigten im Vergleich zu den Kontrollgruppen zudem eine Verbesserung bei drei Komponenten, die jedem dieser Maße zugrunde liegen: erhöhte berufliche Kohärenz, erhöhte physiologische Ausgeglichenheit und erhöhte Zufriedenheit mit dem beruflichen und persönlichen Leben. Diese Studie untersuchte Gesundheit, Stress und Mitarbeiterentwicklung in zwei Umgebungen der Automobilindustrie: einem großen Fertigungswerk eines Fortune-100-Unternehmens und einem kleinen Vertriebsunternehmen. Mitarbeiter, die die TM-Technik erlernten, zeigten signifikant größere Verbesserungen bei einer Vielzahl von Maßen, darunter: verringerte physiologische Erregung; Verringerungen von Angst, beruflicher Anspannung, Insomnie und Erschöpfung; reduzierter Konsum von Zigaretten und Spirituosen; und verbesserte allgemeine Gesundheit.
A35: Sozialverhalten | B35: Soziologisch CP Vol 7 Pg4879 | C35: Rehabilitation | D35: TM im Strafvollzug | F35: 2003 | G35: s | H35: Alexander CN, Walton KG, Goodman R. Walpole study of the Transcendental Meditation program in maximum security prisoners I: cross-sectional differences in development and psychopathology. Journal of Offender Rehabilitation 2003 36(1-4):97-126. Gefängnisinsassen in Massachusetts, USA, die zuvor das Programm der Transzendentalen Meditation erlernt hatten, zeigten im Gegensatz zu Kontrollinsassen eine signifikant höhere psychologische Entwicklung und Bewusstseinsentwicklung sowie eine signifikant geringere Psychopathologie. Signifikante Verbesserungen in der TM-Gruppe umfassten eine verbesserte Ich-Entwicklung (p<,0005), verbesserte zwischenmenschliche Beziehungen (p<,05), verringerte psychopathische Abweichung (p<,01), verringerte Angst (p<,05), verringerte Aggression (p<,05), verringerte Anspannung (p<,05) und verringerte Introversion (p<,05). Diese Ergebnisse weisen das TM-Programm als wirksames Instrument zur Förderung der psychischen Gesundheit und der persönlichen Reifung aus, die für eine dauerhafte Rehabilitation von Hochsicherheitsinsassen erforderlich sind.
A36: Sozialverhalten | B36: Soziologisch | C36: Rehabilitation | D36: TM im Strafvollzug | F36: 2003 | G36: s | H36: Alexander CN, Walton KG, Orme-Johnson DW, Goodman RS, Pallone NJ (eds). Transcendental Meditation in Criminal Rehabilitation and Crime Prevention. Binghamton, New York: Haworth Press, 2003. Vorteile der TM-Technik, die in 4 Gefängnissystemen erlebt wurden, sowie weitreichende Vorteile des TM-Programms, die von Bewährungsprobanden erlebt wurden, die Straftaten von Trunkenheit am Steuer bis hin zu Totschlag begangen hatten. Eine umfassende Zusammenfassung, die die mit der Wahrscheinlichkeit kriminellen Verhaltens und Substanzmissbrauchs verbundenen Risikofaktoren beschreibt und Forschung zusammenfasst, die zeigt, wie das TM-Programm viele dieser Faktoren erfolgreich adressiert. Eine makroskopische Betrachtung der Rolle des TM-Programms in der Straffälligenrehabilitation.
A37: Gesundheit | B37: Physiologisch | C37: Effizienz & Stabilität | D37: Atemveränderungen | F37: 1970 | G37: s | H37: Allison J. Respiratory changes during Transcendental Meditation. Lancet 1970 7651:833. Die Atemfrequenz nahm während der Praxis der TM-Technik ab, was auf einen entspannteren und ausgeruhteren Zustand hinweist.
A38: Gesundheit | B38: Physiologisch | C38: Kardiovaskulär | D38: Verringerter Bluthochdruck | E38: Meta | F38: 2008 | G38: s | H38: Anderson JW, Liu C, Kryscio RJ. Blood pressure response to Transcendental Meditation: a meta-analysis. American Journal of Hypertension 2008 21(3):310-316. Laut einer definitiven neuen Meta-Analyse früherer Studien zu Stressreduktionsprogrammen und hohem Blutdruck erwies sich, dass die Technik der Transzendentalen Meditation eine statistisch signifikante Senkung des hohen Blutdrucks bewirkt – ein Effekt, der bei anderen Formen der Entspannung, Meditation, des Biofeedbacks oder des Stressmanagements nicht gefunden wurde. Der Blutdruck sank in allen TM praktizierenden Gruppen im Vergleich zu den Kontrollgruppen signifikant. Die Blutdrucksenkung betrug im Durchschnitt 5 Punkte beim systolischen und 3 Punkte beim diastolischen Wert. Diese Ergebnisse sind nicht nur statistisch signifikant, sondern auch klinisch signifikant. Es ist zu erwarten, dass diese Ergebnisse zu 15–20 % weniger Herz-Kreislauf-Erkrankungen führen. Jim Anderson und Kollegen von der University of Kentucky bündelten Daten aus neun veröffentlichten, gut kontrollierten Studien mit insgesamt 711 Personen. Die Probanden reichten im Alter von Jugendlichen (15–18 Jahre) bis zu Senioren (mittleres Alter 81,3 ± 9,8 Jahre) und umfassten normotensive, prähypertensive und hypertensive Personen.
A39: Sozialverhalten | B39: Soziologisch | C39: Rehabilitation | D39: TM im Strafvollzug | F39: 2003 | G39: s | H39: Anklesaria FK, King MS. The Enlightened Sentencing Project: a judicial innovation. Journal of Offender Rehabilitation 2003 36(1-4):35-46. Bewährungsprobanden, die zur TM-Technik „verurteilt“ wurden, berichten von weniger Wut und verringertem Substanzmissbrauch. Richter berichten, dass die TM praktizierenden Bewährungsprobanden ein größeres Selbstwertgefühl und mehr Selbstkontrolle, eine positive soziale Einstellung und eine erhöhte Fähigkeit, eine Beschäftigung zu finden, aufweisen. Ab 1996 begann Richter David C. Mason, ein Bezirksrichter in Missouri, Bewährungsprobanden (Straftaten von Trunkenheit am Steuer bis Totschlag) dazu zu verurteilen, die TM-Technik zu erlernen und Kurse zu der Technik zu besuchen. Zum Zeitpunkt der Veröffentlichung dieser Studie im Jahr 2003 hatten 6 Richter in Missouri 100 Bewährungsprobanden zum TM-Programm verurteilt. Auch Bewährungshelfer in Missouri erleben die breite Palette an Vorteilen des TM-Programms. Durch die kreative Nutzung bestehender Gesetze ist das Enlightened Sentencing Project ein Beispiel für erfolgreiche justizielle Innovation zur Deckung eines gesellschaftlichen Bedarfs.
A40: Sozialverhalten | B40: Soziologisch | C40: Rehabilitation | D40: TM im Strafvollzug | F40: 2003 | G40: s | H40: Anklesaria FK, King MS. The Transcendental Meditation program in the Senegalese penitentiary system. Journal of Offender Rehabilitation 2003 36(1-4):303-318. Zwischen 1987 und 1989 wurden mehr als 11.000 Insassen und 900 Justizvollzugsbeamte und Gefängnisverwalter in 31 der 34 Gefängnisse des westafrikanischen Landes Senegal im Programm der Transzendentalen Meditation unterwiesen. Regelverstöße nahmen ab, die medizinischen Kosten sanken um 70 %, und die Rückfallquote fiel von 90 % im Zeitraum vor der Meditation auf weniger als 3 % nach der Einführung des Programms.
A41: Gesundheit | B41: Physiologisch | C41: Motorik & Wahrnehmung | D41: Reaktionszeit | F41: 1974 | G41: s | H41: Appelle S, Oswald LE. Simple reaction time as a function of alertness and prior mental activity. Perceptual and Motor Skills 1974 38(3):1263-1268. Es zeigte sich, dass Probanden, die die Technik der Transzendentalen Meditation praktizierten, vor und nach einer Sitzung der Technik schnellere Reaktionen aufwiesen als andere Probanden vor und nach entweder Ruhe oder einer einfachen Aufgabe.
A42: Gesundheit | B42: Psychologisch | C42: Affektiv | D42: Stressreduktion | F42: 2023 | G42: s | H42: Aquino-Russell C, Aldiabat KM, Alsrayheen E. Experiences of advanced standing program nursing students and instructors practicing Transcendental Meditation. American Journal of Qualitative Research 2023 7(3):32-48. doi.org/10.29333/ajqr/13239. Über die Erfahrungen von Pflegestudierenden und -lehrenden des Advanced Standing Program (ASP), die Transzendentale Meditation® (TM®) praktizieren, ist wenig bekannt. Ziel dieser qualitativen Studie war es, aus den schriftlichen Beschreibungen von ASP-Pflegestudierenden und -lehrenden, die im Praktizieren der TM unterwiesen wurden, Themen herauszuarbeiten, um ein tieferes Verständnis dafür zu gewinnen, welche Bedeutung diese Praxis für ihr Leben und Wohlbefinden haben und wie sie es beeinflussen könnte. Zugleich sollten Wege entdeckt werden, wie die TM als wirksame Intervention zur Stressreduktion und als Gelegenheit zur Verbesserung der pflegerischen Versorgung in die Pflegeausbildung und -praxis integriert werden könnte. Es wurde eine thematische Analyse angewandt. Zwanzig Studierende und drei Lehrende meldeten sich freiwillig und erhielten von zertifizierten TM-Lehrenden Schulungssitzungen über die korrekte Art, TM zweimal täglich zu praktizieren. Schriftliche Beschreibungen wurden über 11 Monate hinweg mittels monatlicher schriftlicher Reflexionstagebücher erhoben. Die Beschreibungen aus den Tagebucheinträgen wurden analysiert und legten Hauptthemen offen, die die Erfahrungen der Teilnehmer beim Praktizieren der TM und die daraus resultierenden positiven Auswirkungen auf ihr Leben hinsichtlich Stressbewältigung, Steigerung der Produktivität und Verbesserung von Beziehungen beschreiben. Abschließend beinhalten die Empfehlungen, die TM als nützliches Instrument zur Stressreduktion in Pflegeprogrammen für Studierende und ihre Lehrenden einzuführen und umzusetzen.
A43: Gesundheit | B43: Psychologisch | C43: Affektiv | D43: Wohlbefinden | E43: RCT | F43: 2024 | G43: s | H43: Aquino-Russell C, Bonamer JI, Hartranft S, Kutash M, Johnson A. Transcendental Meditation enriches nurses’ authentic presence through caring for self and others. Journal of Holistic Nursing 2024 42(4). doi.org/10.1177/08980101241262922. Die übergreifende Multimethodenstudie umfasste eine qualitative thematische Analyse (TA) und eine randomisierte kontrollierte Studie, um das Wohlbefinden klinischer Pflegekräfte nach der Unterweisung und Praxis der TM während der Pandemie zu beschreiben/zu bewerten. Im Rahmen der Studie erhielten die Teilnehmer eine TM-Unterweisung. Befragungen wurden zu Studienbeginn sowie nach 1 und 3 Monaten durchgeführt; die qualitative Komponente war jedoch nur in der 3-Monats-Befragung enthalten. Nach Einreichung der Ausgangsbefragung wurden die Teilnehmer entweder einer sofortigen Unterweisung (Interventionsgruppe) oder einer verzögerten Unterweisung, die nach der abschließenden 3-Monats-Befragung erfolgte (Kontrollgruppe), zugelost. Die qualitative Komponente unserer Studie umfasste eine thematische Analyse zur Beschreibung der Erfahrungen klinischer Pflegekräfte nach der Unterweisung und Praxis der TM während der COVID-19-Pandemie.
A44: Gesundheit | B44: Physiologisch | C44: EEG | D44: TC | F44: 2004 | G44: s | H44: Arenander A, Travis FT. Brain patterns of Self-awareness. In B Beitman, J Nair (eds), Self-Awareness Deficits. New York: WW Norton, 2004. Dieses Kapitel hat das Konzept eines grundlegenden Zustands der Selbstgewahrsamkeit eingeführt, der sowohl als unabhängig als auch als Quelle bewusster Erfahrungen postuliert wird. Die Forschung legt nahe, dass hohe Werte breitbandiger frontaler EEG-Kohärenz mit diesem Grundzustand der Selbstgewahrsamkeit verbunden sind. Dieses grundlegende Gewahrsein könnte als leere Leinwand dienen, auf der wir die sich stetig verändernden Umstände unseres Lebens organisieren, lenken und erfahren. Intakte, hoch synchrone präfrontale Schaltkreise scheinen für die unmittelbare Erfahrung dieses Grundzustands des Gewahrseins entscheidend zu sein, ebenso wie für den Übergang von einer episodischen, meditationsabhängigen Erfahrung dieses Zustands zu seiner allmählichen Entwicklung als koexistierendes Kontinuum über die Wach-, Traum- und Schlafzustände des Bewusstseins hinweg. Unsere Übersicht stützt die Existenz von mindestens zwei primären Modi der Selbstgewahrsamkeit – einem mit und einem ohne Inhalt – sowie die Möglichkeit eines dritten, integrierten Modus, in dem Wissender und Gewusstes, Selbst und Objekte koexistieren. Zukünftige Forschung sollte diesen mutmaßlichen Grund der Selbstgewahrsamkeit und die Folgen seiner wiederholten und systematischen Erfahrung für die Plastizität und Funktion des Gehirns weiter charakterisieren. Sobald eine solche forschungsbasierte Grundlage geschaffen ist, können die verschiedenen, vielfältigen Ausdrucksformen der Selbstgewahrsamkeit besser als fortschreitende Schichten der Verarbeitung und Interaktion zwischen dem Wissenden (Selbstgewahrsamkeit) und dem Gewussten (der inneren und äußeren Umwelt) verstanden werden. Ihrerseits sollten wir dann besser in der Lage sein, die Vielfalt dysfunktionaler Modi der Selbstgewahrsamkeit zu verstehen und wirksam zu behandeln.
A45: Sozialverhalten | B45: Übersichtsarbeit CPVol4 Pg 2894 | C45: Rehabilitation | D45: Verringerter Substanzmissbrauch | F45: 1980 | G45: s | H45: Aron A, Aron EN. The Transcendental Meditation program's effect on addictive behavior. Addictive Behaviors 1980 5(1):3-12. Dieser Beitrag bespricht Forschung, die zeigt, dass das Programm der Transzendentalen Meditation wirksam einer breiten Vielfalt suchtbezogener Verhaltensweisen entgegenwirkt. Die Autoren verorten die Grundlage dieses Effekts in den umfassenden physiologischen, psychologischen und sozialen Vorteilen, die sich nachweislich aus der Transzendentalen Meditation ergeben. – DIE HERAUSGEBER. Der letzte Abschnitt betrachtet praktische Fragen der Umsetzung von TM-Programmen in Settings der Suchtbehandlung und -prävention.
A46: Sozialverhalten | B46: Soziologisch CPVol 3Pg 2158 | C46: Rehabilitation | D46: Verringerter Substanzmissbrauch | F46: 1983 | G46: s | H46: Aron A, Aron EN. The pattern of reduction of drug and alcohol use among Transcendental Meditation participants. Bulletin of the Society of Psychologists in Addictive Behaviors 1983 2(1):28-33. Es zeigte sich, dass die Praxis der Technik der Transzendentalen Meditation zu einem verringerten Konsum von Tabak, Alkohol und Marihuana führte. Das beobachtete Muster war das eines fortschreitenden, innerlich motivierten Rückgangs des Drogenkonsums als natürliche Folge positiver Entwicklungen im Leben der Person. – DIE HERAUSGEBER. Neuere Studien legen nahe, dass der Substanzmissbrauch allmählich zurückgeht und der Konsum nach etwa 2 Jahren Praxis der Transzendentalen Meditation (TM) meist aufhört, obwohl die Technik selten zu diesem Zweck erlernt wird. Viele berichteten, dass sie die Substanzen als weniger genussvoll empfanden oder eine wachsende Empfindlichkeit gegenüber deren nachteiligen physiologischen Wirkungen entwickelten.
A47: Geistiges Potenzial | B47: Psychologisch CPVol3 Pg1977 | C47: Intelligenz, Lernen und akademische Leistung, kognitiv und affektiv | D47: Verbesserte akademische Leistung, größere moralische & soziale Reife | F47: 1981 | G47: s | H47: Aron A, Orme-Johnson D, Brubaker P. The Transcendental Meditation program in the college curriculum: a four-year longitudinal study of effects on cognitive and affective functioning. College Student Journal 1981 15(2):140-146. Diese Studie fand Verbesserungen der akademischen Leistung, eine größere moralische Reife, eine erhöhte Orientierung an positiven Werten, eine erhöhte Intelligenz, ein erhöhtes Selbstvertrauen, eine erhöhte Geselligkeit, eine verbesserte psychische Gesundheit und ein Wachstum der sozialen Reife bei College-Studierenden, die die TM-Technik praktizieren.
A48: Sozialverhalten | B48: Psychologisch CPVol4 Pg2474 | C48: Affektiv | D48: Eheliche Zufriedenheit & Anpassung | F48: 1982 | G48: s | H48: Aron EN, Aron A. Transcendental Meditation and marital adjustment. Psychological Reports 1982 51(7):887-890. Diese Studie fand eine erhöhte eheliche Zufriedenheit und Anpassung bei Paaren, die die TM-Technik praktizieren. Verheiratete Frauen, die die Technik der Transzendentalen Meditation erlernt hatten, zeigten eine größere eheliche Zufriedenheit als gematchte nicht meditierende Kontrollpersonen. Dieses Ergebnis war bei Frauen, die ihre Praxis der Technik der Transzendentalen Meditation regelmäßig ausübten, signifikant größer.
A49: Weltfrieden | B49: Soziologisch CPVol 6Pg 4101 | C49: Lebensqualität | D49: Maharishi-Effekt: Nation | F49: 1995 | G49: s | H49: Assimakis PD, Dillbeck MC. Time series analysis of improved quality of life in Canada: social change, collective consciousness, and the TM-Sidhi program. Psychological Reports 1995 76(3):1171-1193. Verbesserte Qualität des nationalen Lebens: Verbesserungen bei einem wöchentlichen Index, der Verkehrstote, Tötungsdelikte und Suizide umfasst (Kanada, 1983–1985); Verbesserungen bei einem monatlichen Index, der Verkehrstote, Tötungsdelikte, Suizide, Zigarettenkonsum und durch Streiks verlorene Arbeitstage umfasst (Kanada, 1972–1986). In Kanada wurden verringerte gewaltsame Todesfälle festgestellt, wenn die Größe der Gruppe der Maharishi University of Management die Quadratwurzel aus einem Prozent der Gesamtbevölkerung der USA und Kanadas überschritt. Die beiden in diesem Beitrag berichteten Studien fanden eine verbesserte Qualität des nationalen Lebens in Kanada in Zeiträumen, in denen die Größe der Gruppe der Teilnehmer am Transzendentale-Meditation-Sidhi-Programm in den USA die Quadratwurzel aus einem Prozent der kombinierten nationalen Bevölkerung der USA und Kanadas überschritt. Die erste Studie fand eine signifikante Verbesserung bei einem wöchentlichen Index, gemessen als Summe von Verkehrstoten, Tötungsdelikten und Suiziden; die zweite Studie dokumentierte eine signifikante Verbesserung bei einem monatlichen Index, der die Variablen Verkehrstote, Tötungsdelikte, Suizide, Zigarettenkonsum und durch Streiks verlorene Arbeitstage kombinierte.
A50: Gesundheit | B50: Physiologisch | C50: Affektiv | D50: Stressreduktion | F50: 2020 | G50: s | H50: Avvenuti G, Leoa A, Cecchettia L, Franco MF, Travis F, Caramellad D, Bernardia G, Ricciardia E, Pietrini P. Reductions in perceived stress following Transcendental Meditation practice are associated with increased brain regional connectivity at rest. Brain and Cognition 2020 139:105517. doi.org/10.1016/j.bandc.2020.105517. Die Transzendentale Meditation (TM) wird als ein mentaler Prozess des Transzendierens mittels eines stillen Mantras definiert. Frühere Arbeiten zeigten, dass ein relativ kurzer Zeitraum der TM-Praxis zu einer Verringerung von Stress und Angst führt. Ob diese Veränderungen jedoch durch spezifische morpho-funktionelle Gehirnveränderungen (wie bei anderen Meditationstechniken beobachtet) gestützt werden, ist noch unklar. Mit einem Längsschnittdesign kombinierten wir psychometrische Fragebögen sowie strukturelle und funktionelle Ruhezustands-Magnetresonanztomografie (RS-fMRT), um die möglichen Gehirnveränderungen zu untersuchen, die den psychologischen Wirkungen der TM zugrunde liegen. Die endgültige Stichprobe umfasste 19 unerfahrene Probanden, die angewiesen wurden, zwei tägliche 20-minütige TM-Sitzungen zu absolvieren, sowie 15 Freiwillige in der Kontrollgruppe. Beide Gruppen wurden bei der Rekrutierung (T0) und nach 3 Monaten (T1) untersucht. Bei T1 zeigten nur die Meditierenden eine Verringerung der wahrgenommenen Angst und des Stresses (t(18) = 2,53, p = 0,02), die negativ mit den T1-T0-Veränderungen der funktionellen Konnektivität zwischen dem posterioren cingulären Kortex (PCC), dem Precuneus und dem linken oberen Parietallappen korrelierte. Zusätzlich war die TM-Praxis mit einer erhöhten Konnektivität zwischen PCC und rechter Insula verbunden, was wahrscheinlich Veränderungen der interozeptiven Wahrnehmung widerspiegelt. Bei Meditierenden oder Kontrollpersonen wurden keine strukturellen Veränderungen beobachtet. Diese vorläufigen Befunde weisen darauf hin, dass die positiven Wirkungen der TM durch funktionelle Gehirnveränderungen vermittelt werden können, die nach einer kurzen Praxisdauer von 3 Monaten auftreten.
A51: Gesundheit | B51: Psychologisch | C51: Affektiv | D51: Verringerte Insomnie, Angst, Depression, Stress | F51: 2021 | G51: x | H51: Azizoddin DR, Kvaternik N, Beck M, Zhou G, Hasdianda MA, Jones N, Johnsky L, Im D, Chai PR, Boyer EW. Heal the Healers: a pilot study evaluating the feasibility, acceptability, and exploratory efficacy of a Transcendental Meditation intervention for emergency clinicians during the coronavirus disease 2019 pandemic. Journal of the American College of Emergency Physicians Open 2021 2(6):e12619. doi.org/10.1002/emp2.12619 Abstract Zielsetzung: Notfallmediziner weisen erhöhte Burnout-Raten auf, die zu schlechten Ergebnissen für Behandelnde, Patienten und Gesundheitssysteme führen. Ziel dieser einarmigen Pilotstudie war es, die Durchführbarkeit einer Intervention mit Transzendentaler Meditation (TM) für Notfallmediziner während der Coronavirus-Pandemie 2019 (COVID-19) zu bewerten und die mögliche Wirksamkeit hinsichtlich der Verbesserung von Burnout, Schlaf und psychischer Gesundheit zu untersuchen. Methoden: Notfallmediziner (Ärzte, Pflegekräfte und Arzthelfer) aus zwei städtischen Krankenhäusern wurden für eine dreimonatige TM-Unterweisung (8 Einzel- oder Gruppensitzungen in Präsenz und aus der Ferne) rekrutiert. Die Sitzungsteilnahme war das primäre Durchführbarkeitskriterium (vorab festgelegt als Teilnahme an 6/8 Sitzungen), und Burnout war das primäre klinische Zielkriterium. Von den Teilnehmern berichtete Durchführbarkeitsmaße sowie validierte Maße für Burnout, Depression, Angst, Schlafstörungen und Stress wurden zu Studienbeginn sowie bei den Nachuntersuchungen nach 1 und 3 Monaten erhoben. Es wurden deskriptive Statistiken und lineare gemischte Modelle verwendet. Ergebnisse: Von den teilnehmenden 14 Ärzten (46 %), 7 Pflegekräften (22 %) und 10 Arzthelfern (32 %) waren 61 % weiblich (n = 19/32). Das TM-Training und die häusliche Meditationspraxis waren für die Behandelnden durchführbar, da 90,6 % (n = 29/32) an 6/8 Trainingssitzungen teilnahmen und 80,6 % angaben, im Durchschnitt mindestens einmal täglich zu meditieren. Die Teilnehmer zeigten signifikante Verringerungen des Burnouts (p < ,05; Effektstärken Cohens d = 0,43–0,45) sowie der Symptome von Depression, Angst, Stress und Schlafstörungen (p-Werte < ,001; Cohens d = 0,70–0,87).
A52: Gesundheit | B52: Physiologisch CPVol 3 Pg1666 | C52: EEG | D52: TC | F52: 1984 | G52: s | H52: Badawi K, Wallace RK, Orme-Johnson D, Rouzeré A-M. Electrophysiologic characteristics of respiratory suspension periods occurring during the practice of the Transcendental Meditation program. Psychosomatic Medicine 1984 46(3):267-276. Es zeigte sich, dass die Kombination aus innerer Wachheit, Atempause (respiratorischer Suspension) und hoher EEG-Kohärenz den Zustand des transzendentalen Bewusstseins kennzeichnet, der während der Praxis der Technik der Transzendentalen Meditation erlebt wird.
A53: Gesundheit | B53: Physiologisch | C53: Kardiovaskulär | D53: Verringerter Bluthochdruck | E53: Meta | F53: 2015 | G53: s | H53: Bai Z, Chang J, Chen C, Li P, Yang K, Chi I. Investigating the effect of transcendental meditation on blood pressure: a systematic review and meta-analysis. Journal of Human Hypertension 2015 29:653–662. doi:10.1038/jhh.2015.6. Zwölf Studien mit 996 Teilnehmern wurden ausgewertet, um die Wirkung der TM auf die Blutdruckwerte zu untersuchen. Die Studien legten nahe, dass sich die Senkung des systolischen und diastolischen Blutdrucks zwischen den TM-Gruppen und den Kontrollgruppen signifikant unterschied, mit ungefähren Senkungen von 4,26 mmHg bzw. 2,33 mmHg bei den Teilnehmern der TM-Gruppen. Dies weist darauf hin, dass die TM das Risiko für Herz-Kreislauf-Erkrankungen durch eine signifikante Blutdrucksenkung verringern kann. Die Heterogenität zwischen den einbezogenen Studien war gering und wurde durch Subgruppenanalysen aufgelöst, bedingt durch die große Variation in Interventionsdauer und Teilnehmerdemografie (Blutdruckniveau, Geschlecht und Alter). Auf Grundlage der Ergebnisse der Subgruppenanalysen beobachteten wir zwei interessante Phänomene. Die TM hatte eine größere Wirkung auf Personen über 65 Jahre, auf Personen mit einem anfänglichen systolischen Blutdruck über 140 mmHg und auf Frauen – jeweils im Vergleich zu jüngeren Teilnehmern (unter 65 Jahren), Personen mit einem anfänglichen systolischen Blutdruck von 120–139 mmHg und Männern.
A54: Gesundheit | B54: Psychologisch | C54: Affektiv | D54: PTBS bei Universitätsstudierenden | F54: 2019 | G54: s | H54: Bandy C, Dillbeck M, Sezibera V, Taljaard L, de Reuck J, Wilks M, Shapiro D, Peycke R. Reduction of PTSD in South African university students using Transcendental Meditation practice. Psychological Reports 2019 (February) online. doi:10.1177/0033294119828036. Es wurde eine Studie an südafrikanischen College-Studierenden durchgeführt, die die Technik der Transzendentalen Meditation nutzten, um die posttraumatische Belastungsstörung zu verringern. Studierende, die die Kriterien für eine mögliche posttraumatische Belastungsstörung erfüllten, wurden einbezogen. Vierunddreißig Studierende an der Experimentaluniversität in Südafrika, bei denen klinisch eine posttraumatische Belastungsstörung diagnostiziert worden war, wurden in der Technik der Transzendentalen Meditation unterwiesen und praktizierten sie zweimal täglich, verglichen mit 34 diagnostizierten PTBS-Vergleichsstudierenden an der Vergleichsuniversität. Der multivariate Effekt war sowohl für die PTBS-Symptomatik als auch für die Depression signifikant. Die Ergebnisse waren signifikant mit der Regelmäßigkeit der Praxis assoziiert. Die Studie repliziert jüngste Befunde und bietet eine alternative pädagogische Behandlung für die Hochschulbildung.
A55: Geistiges Potenzial & Gesundheit | B55: Physiologisch | C55: EEG | D55: TC: einzigartiger Zustand ruhevoller Wachheit | F55: 1973 | G55: s | H55: Banquet JP. Spectral analysis of the EEG in meditation. Electroencephalography and Clinical Neurophysiology 1973 35(2):143-151. Probanden, die die Technik der Transzendentalen Meditation praktizierten, zeigten charakteristische EEG-Veränderungen, darunter langsame Alpha-Aktivität mit hoher Amplitude, die sich bis zu den anterioren Kanälen ausdehnte; Theta-Aktivität, die sich vom Schlaf unterscheidet; rhythmische, amplitudenmodulierte Beta-Wellen über der gesamten Kopfhaut; und eine Synchronisation der anterioren und posterioren Kanäle.
A56: Geistiges Potenzial & Gesundheit | B56: Physiologisch CPVol 3 Pg1921 | C56: EEG | D56: TC+: Zunahme von Vigilanz und selektiver Aufmerksamkeit | F56: 1980 | G56: s | H56: Banquet JP, Lesèvre N. Event-related potentials in altered states of consciousness. Progress in Brain Research 1980 54:447-453. Es zeigte sich, dass Praktizierende des Programms der Transzendentalen Meditation schnellere Reaktionen mit weniger Fehlern sowie eine kürzere Latenz und größere Amplitude visuell evozierter Potenziale aufwiesen, was auf eine Zunahme der Fähigkeit zur selektiven Aufmerksamkeit und ein verbessertes Vigilanzniveau hinweist. Anmerkung: In diesem Beitrag bezieht sich der Ausdruck „veränderte Bewusstseinszustände“ auf höhere Bewusstseinszustände, die durch das TM-Programm entwickelt werden.
A57: Geistiges Potenzial & Gesundheit | B57: Physiologisch | C57: EEG | D57: TC: einzigartiger Zustand ruhevoller Wachheit | F57: 1974 | G57: s | H57: Banquet JP, Sailhan M. Analyse E.E.G. d’états de conscience induits et spontanés. Revue d’Electroencéphalographie et de Neurophysiologie Clinique 1974 4(3):445-453. Es wurden signifikante Unterschiede zwischen der TM-Technik und der Entspannung sowie zwischen der TM-Technik und den Schlafstadien I und II festgestellt.
A58: Gesundheit | B58: Psychologisch | C58: Affektiv | D58: PTBS | F58: 2018 | G58: s | H58: Barnes VA. Transcendental Meditation and treatment for post-traumatic stress disorder (Editorial comment). The Lancet Psychiatry 2018 5(12):946-947. doi.org/10.1016/S2215-0366(18)30423-1. Eine zentrale Herausforderung der Militärmedizin war in den letzten Jahren die Behandlung der psychischen Gesundheit von Militärangehörigen, die in Einsätzen entsandt wurden. Der wirksamste Behandlungsverlauf für die posttraumatische Belastungsstörung (PTBS) wird intensiv debattiert und steht aufgrund der großen Zahl von aus dem Einsatz zurückkehrenden Angehörigen mit PTBS im Mittelpunkt der militärischen Gemeinschaft. Mehr als ein Drittel der Patienten mit PTBS erholt sich selbst nach vielen Jahren nicht, was zeigt, dass die PTBS eine chronische und kostspielige Erkrankung für die Angehörigen, ihre Familien und die Gesellschaft insgesamt ist. Die traditionelle Behandlung der PTBS war aufgrund von Komorbiditäten, Nebenwirkungen der medikamentösen Therapie sowie des für die Psychotherapie erforderlichen Zeit- und Energieaufwands nicht durchgängig erfolgreich. Die Pharmakotherapie hat sich bei der Behandlung der PTBS als unzureichend nützlich erwiesen, während die Therapietreue und der Behandlungserfolg verschiedener Psychotherapien enttäuschend waren. Wenn Patienten mit PTBS nicht auf die traditionelle Behandlung ansprechen, sollten neue Ansätze in Betracht gezogen werden.
A59: Sozialverhalten | B59: Psychologisch Stressreduktion CPVol 7 Pg4798 | C59: Persönlichkeitsentwicklung | D59: Bildung, Verhalten von Jugendlichen | E59: RCT | F59: 2003 | G59: s | H59: Barnes VA, Bauza LB, Treiber FA. Impact of stress reduction on negative school behavior in adolescents. Health and Quality of Life Outcomes 2003 1(1):10. Diese randomisiert zugeteilte Studie ergab, dass jugendliche Schüler, die die Technik der Transzendentalen Meditation erlernten und an täglicher Gruppenpraxis teilnahmen, im Gegensatz zu Kontrollschülern, die täglich für eine gleich lange Zeit an einem Gesundheitsbildungskurs teilnahmen, verringerte Fehlzeiten, weniger Verstöße gegen die Schulordnung und weniger Suspendierungstage aufgrund von Verhaltensproblemen zeigten. Die TM-Gruppe wies niedrigere Raten an Fehlzeiten, Suspendierungen und Verstößen gegen die Schulordnung auf als die Kontrollgruppe.
A60: Gesundheit | B60: Physiologisch | C60: Kardiovaskulär | D60: Verringerte linksventrikuläre Masse | E60: RCT | F60: 2012 | G60: s | H60: Barnes VA, Kapuku GK, Treiber FA. Impact of Transcendental Meditation on left ventricular mass in African American adolescents. Evidence-Based Complementary and Alternative Medicine 2012 923153. doi:10.1155/2012/923153. Eine erhöhte linksventrikuläre Masse (LVM) ist seit Langem als Risikofaktor für koronare Herzkrankheit (KHK), Herzinsuffizienz, Schlaganfall, Herzrhythmusstörungen und plötzlichen Tod bekannt. Ein frühes Anzeichen des ventrikulären Remodelings ist eine erhöhte linksventrikuläre Masse (LVM), die im Laufe der Zeit zu einer Linksherzhypertrophie führen kann – dem stärksten Prädiktor für kardiovaskuläre Morbidität und Mortalität, abgesehen vom fortschreitenden Alter. Die erfolgreiche Umsetzung der Intervention weist auf das Potenzial schulbasierter Stressreduktionsprogramme als Mittel zur Verringerung der Wahrscheinlichkeit eines frühen Auftretens einer LVH (Linksherzhypertrophie) bei Risikojugendlichen hin. Diese Befunde weisen darauf hin, dass bei einer Gruppe prähypertensiver afroamerikanischer Jugendlicher 4 Monate TM im Vergleich zur Gesundheitsbildung zu einer signifikanten Verringerung des LVMI führten, und dass diese Veränderungen bei der 4-Monats-Nachuntersuchung erhalten blieben. Methoden. 62 (30 TM; 32 Kontrolle) afroamerikanische Jugendliche (Alter 16,2 ± 1,3 Jahre) mit hochnormalem systolischem Blutdruck wurden randomisiert entweder einer 4-monatigen Transzendentale-Meditation-(TM)- oder einer Gesundheitsbildungs-Kontrollgruppe zugeteilt. Das echokardiografisch abgeleitete Maß des LVM-Index (LVMI = LVM/ht2,7) wurde vor und nach der 4-monatigen TM-Studie sowie bei der 4-Monats-Nachuntersuchung gemessen. Zur Bestimmung des LVMI wurde eine 2D-geführte M-Mode-Echokardiografie mit einem Hewlett-Packard-5500-Echosonografen verwendet. Ergebnisse. Die TM-Gruppe zeigte bei der 4-Monats-Nachuntersuchung im Vergleich zur Kontrollgruppe eine stärkere Verringerung des LVMI (−2,6 gegenüber +0,3 g/ht2,7, p < 0,04). Die TM-Gruppe zeigte bei der 4-Monats-Nachuntersuchung im Vergleich zur Kontrollgruppe einen geringeren Anstieg des BMI (0,2 ± 1,6 gegenüber 1,1 ± 1,4, p < 0,03).
